{
  "brand": "seloger",
  "id": "25PS1X2U8A7W",
  "metadata": {
    "legacyId": "255838605",
    "creationDate": "2025-12-04T14:09:00Z",
    "updateDate": "2025-12-04T14:10:19.108Z",
    "status": {
      "status": true,
      "enrichments": {
        "contactSettings": false,
        "geo": false,
        "intermediary": false,
        "media": false,
        "onlineId": false
      }
    },
    "isNewBuildProject": false
  },
  "sections": {
    "location": {
      "address": {
        "country": "FRA",
        "city": "Lyon 4ème",
        "zipCode": "69004"
      },
      "isAddressPublished": true,
      "geometry": {
        "type": "MultiPolygon",
        "coordinates": [
          [
            [
              [
                4.84132,
                45.77947
              ],
              [
                4.84306,
                45.77878
              ],
              [
                4.83987,
                45.77331
              ],
              [
                4.8351,
                45.77552
              ],
              [
                4.83469,
                45.77455
              ],
              [
                4.8238,
                45.77373
              ],
              [
                4.81287,
                45.7713
              ],
              [
                4.80897,
                45.77606
              ],
              [
                4.81195,
                45.78202
              ],
              [
                4.81901,
                45.78979
              ],
              [
                4.82241,
                45.78778
              ],
              [
                4.8215,
                45.78692
              ],
              [
                4.82362,
                45.7843
              ],
              [
                4.82927,
                45.78259
              ],
              [
                4.83172,
                45.78297
              ],
              [
                4.83116,
                45.7821
              ],
              [
                4.83272,
                45.78167
              ],
              [
                4.83775,
                45.78262
              ],
              [
                4.84132,
                45.77947
              ]
            ]
          ]
        ]
      }
    },
    "description": {
      "description": "BAIL CIVIL - T2 DUPLEX - LYON 4\r\n38 Cours d'Herbouville LYON 69004\r\n\r\nVisites prévues le mardi 9 décembre de 15h à 16h30. Merci de nous appeler afin de fixer un RDV.\r\n\r\nVenez découvrir cet appartement duplex de 25,09m2 situé au 1er étage accessible depuis la cour.\r\n\r\n\r\nCaractéristiques du logement :\r\n\r\nRez-de-chaussée :\r\nUne cuisine meublée et équipée ouverte sur séjour.\r\n\r\nA l'étage:\r\nUn espace nuit composé d'une chambre avec une salle d'eau.\r\n\r\nDisponible à partir du 9/12/2025\r\n\r\nEncadrement des loyers :\r\n\r\n* Loyer hors charges : 940,00€\r\n* Complément de loyer : 428,16€ compris dans le loyer hors charges (justifié par une rénovation récente, une cuisine équipée et meublée)\r\n* Charges locatives : 10,00€ (comprenant l'entretien des parties communes)\r\n\r\nTOTAL MENSUEL : 950,00€\r\nDépôt de garantie : 1880,00€\r\n\r\nMontant de loyer de référence : 17,00€/m2\r\nMontant de loyer majoré : 20,40€/m2\r\n\r\nFrais de mise en location et d'état des lieux :\r\n\r\n* Frais d'agence : 250,90€\r\n* Frais d'état des lieux : 75,27€\r\n\r\nPour déposer votre candidature :\r\n\r\nZéro papier & démarche simplifiée !\r\nTous les dossiers de candidatures sont à déposer en ligne sur notre site. Rubrique Louer > Dossier de candidature > Lien ZeloK\r\nLes dossiers incomplets ne pourront être étudiés",
      "texts": [
        {
          "text": "BAIL CIVIL - T2 DUPLEX - LYON 4\r\n38 Cours d'Herbouville LYON 69004\r\n\r\nVisites prévues le mardi 9 décembre de 15h à 16h30. Merci de nous appeler afin de fixer un RDV.\r\n\r\nVenez découvrir cet appartement duplex de 25,09m2 situé au 1er étage accessible depuis la cour.\r\n\r\n\r\nCaractéristiques du logement :\r\n\r\nRez-de-chaussée :\r\nUne cuisine meublée et équipée ouverte sur séjour.\r\n\r\nA l'étage:\r\nUn espace nuit composé d'une chambre avec une salle d'eau.\r\n\r\nDisponible à partir du 9/12/2025\r\n\r\nEncadrement des loyers :\r\n\r\n* Loyer hors charges : 940,00€\r\n* Complément de loyer : 428,16€ compris dans le loyer hors charges (justifié par une rénovation récente, une cuisine équipée et meublée)\r\n* Charges locatives : 10,00€ (comprenant l'entretien des parties communes)\r\n\r\nTOTAL MENSUEL : 950,00€\r\nDépôt de garantie : 1880,00€\r\n\r\nMontant de loyer de référence : 17,00€/m2\r\nMontant de loyer majoré : 20,40€/m2\r\n\r\nFrais de mise en location et d'état des lieux :\r\n\r\n* Frais d'agence : 250,90€\r\n* Frais d'état des lieux : 75,27€\r\n\r\nPour déposer votre candidature :\r\n\r\nZéro papier & démarche simplifiée !\r\nTous les dossiers de candidatures sont à déposer en ligne sur notre site. Rubrique Louer > Dossier de candidature > Lien ZeloK\r\nLes dossiers incomplets ne pourront être étudiés"
        }
      ],
      "headline": "BAIL CIVIL - T2 DUPLEX - LYON 4"
    },
    "hardFacts": {
      "title": "Appartement à louer",
      "keyfacts": [
        "2 pièces",
        "1 chambre",
        "25,1 m²",
        "1er étage"
      ],
      "facts": [
        {
          "type": "numberOfRooms",
          "value": "2 pièces",
          "splitValue": "2",
          "label": "pièces"
        },
        {
          "type": "numberOfBedrooms",
          "value": "1 chambre",
          "splitValue": "1",
          "label": "chambre"
        },
        {
          "type": "livingSpace",
          "value": "25,1 m²",
          "splitValue": "25,1",
          "label": "m²"
        },
        {
          "type": "numberOfFloors",
          "value": "1er étage",
          "splitValue": "1er",
          "label": "étage"
        }
      ],
      "price": {
        "value": "950 €",
        "formatted": "950 €/mois",
        "modifiers": "/mois",
        "unitPostfix": {
          "unitTime": "/mois"
        },
        "additionalInformation": "charges comprises",
        "addition": {
          "value": "cc",
          "priceLabelDesc": "charges comprises"
        },
        "financialLink": {
          "href": "https://www.nextories.com/partner/landing/seloger?utm_source=seloger&utm_medium=nativelien-prix-loc-2&utm_campaign=nativelienprix-pagesdetails-seloger-location2",
          "label": "Demander un financement",
          "partnerName": "NEXTORIES_RESERVEZ"
        },
        "ariaLabel": "950 €",
        "chargesLabel": "cc"
      }
    },
    "energy": {
      "features": [
        {
          "type": "heatingSystem",
          "label": "Type de chauffage",
          "value": "Chauffage individuel"
        }
      ],
      "certificates": [
        {
          "key": "a57e1712-a264-461c-8384-e66230a4024d",
          "scales": [
            {
              "key": "ba5f9082-2ef3-4af9-bb2c-e23a5569e4b7",
              "name": "Diagnostic de Performance Énergétique (DPE)",
              "alternateText": "Un certificat énergétique n'est pas nécessaire pour ce bien.",
              "ariaLabel": "Un certificat énergétique n'est pas nécessaire pour ce bien."
            }
          ]
        }
      ],
      "hasScales": true
    },
    "key": {
      "keys": [
        {
          "label": "Identifiant",
          "value": "255838605"
        },
        {
          "label": "Référence annonce",
          "value": "38HERBOUVILLE"
        }
      ]
    },
    "price": {
      "base": {
        "main": {
          "label": "Loyer charges comprises",
          "value": "940 €/mois Loyer de base",
          "ariaLabel": "940 €/mois Loyer de base"
        },
        "details": [
          {
            "label": "Coûts supplémentaires",
            "value": "10 €/mois",
            "ariaLabel": "10 €"
          },
          {
            "label": "Loyer charges comprises",
            "value": "950 €/mois",
            "ariaLabel": "950 €"
          },
          {
            "label": "Prix ​​au m²",
            "value": "37,47 €/mois/m²",
            "ariaLabel": "37,47 euros par mètre carré"
          },
          {
            "label": "Dépôt de garantie",
            "value": "1880"
          }
        ]
      }
    },
    "features": {
      "preview": [
        {
          "icon": "floors",
          "value": "1er étage"
        },
        {
          "icon": "kitchen",
          "value": "Cuisine intégrée"
        },
        {
          "icon": "balcony",
          "value": "Pas de balcon"
        },
        {
          "value": "Sans vis-à-vis",
          "icon": "with-view"
        },
        {
          "icon": "furnished",
          "value": "Meublé"
        },
        {
          "icon": "bedroom",
          "value": "1 chambre"
        },
        {
          "icon": "barrier-free",
          "value": "Non accessible aux personnes à mobilité réduite"
        },
        {
          "icon": "livingRoom",
          "value": "Salon (total 5,6 m²)"
        }
      ],
      "details": null
    },
    "gallery": {
      "images": [
        {
          "key": "75d8e58c-a75f-4118-ac32-bab798128030",
          "url": "https://mms.seloger.com/7/5/d/8/75d8e58c-a75f-4118-ac32-bab798128030.jpg?ci_seal=ffb0d1fa81fd3a19f810f35f0925991effea2c84",
          "alt": "Appartement à louer 950 € 2 pièces 1 chambre 25,1 m² 1er étage Lyon 4ème 69004",
          "classification": {
            "name": "STAIRCASE",
            "version": "scene-classification-sagemaker-endpoint-live-1-3-10"
          }
        },
        {
          "key": "338fddce-e26a-4343-a230-bae351aab293",
          "url": "https://mms.seloger.com/3/3/8/f/338fddce-e26a-4343-a230-bae351aab293.jpg?ci_seal=3015052a311f9110b4d369237eb7c588398e49fb",
          "classification": {
            "name": "LIVING_ROOM",
            "version": "scene-classification-sagemaker-endpoint-live-1-3-10"
          }
        },
        {
          "key": "b169243f-cc2d-4bbd-95f3-144df5e4a49d",
          "url": "https://mms.seloger.com/b/1/6/9/b169243f-cc2d-4bbd-95f3-144df5e4a49d.jpg?ci_seal=3c14fc3af177d3f6b703df6db21c887b99ebaa17",
          "classification": {
            "name": "KITCHEN",
            "version": "scene-classification-sagemaker-endpoint-live-1-3-10"
          }
        },
        {
          "key": "877f44a3-d00d-4a15-8308-84061c0ed965",
          "url": "https://mms.seloger.com/8/7/7/f/877f44a3-d00d-4a15-8308-84061c0ed965.jpg?ci_seal=95d876d3cfe34dca605d1540d414c0c27ee2c66d",
          "classification": {
            "name": "BEDROOM",
            "version": "scene-classification-sagemaker-endpoint-live-1-3-10"
          }
        },
        {
          "key": "0507ff85-e68e-4e89-8aaa-e730f87833cc",
          "url": "https://mms.seloger.com/0/5/0/7/0507ff85-e68e-4e89-8aaa-e730f87833cc.jpg?ci_seal=1767e6d40aaf86a3834b709c44424c4b3931513d",
          "classification": {
            "name": "BEDROOM",
            "version": "scene-classification-sagemaker-endpoint-live-1-3-10"
          }
        },
        {
          "key": "58e5ecba-0117-468a-b7b5-2477b16c9aab",
          "url": "https://mms.seloger.com/5/8/e/5/58e5ecba-0117-468a-b7b5-2477b16c9aab.jpg?ci_seal=df8060e32f23723032653728b560d2a9f4bb59ef",
          "classification": {
            "name": "BATHROOM",
            "version": "scene-classification-sagemaker-endpoint-live-1-3-10"
          }
        }
      ]
    },
    "documents": {
      "display": false,
      "files": []
    },
    "enrichedMedia": {
      "medias": []
    },
    "mortgage": {
      "brand": "seloger",
      "id": "255838605",
      "federalStateGeoId": "AD04FR31",
      "zip": "69004",
      "city": "Lyon 4ème",
      "country": "FRA",
      "region": "Auvergne-Rhône-Alpes",
      "showRentLabel": true,
      "showMonthlyRateLabel": false,
      "price": 0,
      "prov": 0,
      "monthlyAmount": 0,
      "formattedMonthlyAmount": "0"
    },
    "partnerAd": {
      "showPartnerAd": false
    },
    "sellerLeadLink": {},
    "priceComparison": {
      "data": {
        "value": 17.24,
        "accuracy": 5,
        "high": "26,76",
        "low": "12,73"
      },
      "markerPosition": 100,
      "hasMainPrice": true,
      "isSale": false,
      "pricePerSqm": "37,47",
      "legalText": "Le prix au m2 est automatiquement calculé par Se Loger en fonction du prix de vente et du nombre de m2 du bien. La comparaison est réalisée à partir des informations relatives au prix du marché sur le même secteur dont dispose Se Loger. Cette information ne préjuge en aucun cas de l'évaluation du bien, qui dépend de son état, ses caractéristiques et de sa localisation."
    },
    "mainDescription": {
      "headline": "BAIL CIVIL - T2 DUPLEX - LYON 4",
      "description": "BAIL CIVIL - T2 DUPLEX - LYON 4\r\n38 Cours d'Herbouville LYON 69004\r\n\r\nVisites prévues le mardi 9 décembre de 15h à 16h30. Merci de nous appeler afin de fixer un RDV.\r\n\r\nVenez découvrir cet appartement duplex de 25,09m2 situé au 1er étage accessible depuis la cour.\r\n\r\n\r\nCaractéristiques du logement :\r\n\r\nRez-de-chaussée :\r\nUne cuisine meublée et équipée ouverte sur séjour.\r\n\r\nA l'étage:\r\nUn espace nuit composé d'une chambre avec une salle d'eau.\r\n\r\nDisponible à partir du 9/12/2025\r\n\r\nEncadrement des loyers :\r\n\r\n* Loyer hors charges : 940,00€\r\n* Complément de loyer : 428,16€ compris dans le loyer hors charges (justifié par une rénovation récente, une cuisine équipée et meublée)\r\n* Charges locatives : 10,00€ (comprenant l'entretien des parties communes)\r\n\r\nTOTAL MENSUEL : 950,00€\r\nDépôt de garantie : 1880,00€\r\n\r\nMontant de loyer de référence : 17,00€/m2\r\nMontant de loyer majoré : 20,40€/m2\r\n\r\nFrais de mise en location et d'état des lieux :\r\n\r\n* Frais d'agence : 250,90€\r\n* Frais d'état des lieux : 75,27€\r\n\r\nPour déposer votre candidature :\r\n\r\nZéro papier & démarche simplifiée !\r\nTous les dossiers de candidatures sont à déposer en ligne sur notre site. Rubrique Louer > Dossier de candidature > Lien ZeloK\r\nLes dossiers incomplets ne pourront être étudiés",
      "metadata": {
        "language": "fr"
      }
    },
    "areaDescription": {
      "headline": "Emplacement"
    },
    "extendedInfoDescription": {
      "headline": "Informations supplémentaires"
    },
    "statistics": {
      "published": "5 jours en ligne",
      "views": "51 vues",
      "saves": "3 favoris"
    }
  },
  "contactSections": {
    "id": "25PS1X2U8A7W",
    "legacyId": "255838605",
    "brand": "seloger",
    "agencyId": "RC-019240",
    "static": {
      "phoneNumbers": [
        "+33787892946 / 0981689689"
      ]
    },
    "sticky": {
      "phoneNumbers": [
        "+33787892946 / 0981689689"
      ]
    },
    "contactCard": {
      "title": "GRAND LYON IMMOBILIER",
      "subtitle": "Lola Mallin",
      "phoneNumbers": [
        "+33787892946 / 0981689689"
      ],
      "isPrivateOwner": false,
      "agencyLogo": {
        "logoUrl": "https://mms.seloger.com/1/0/0/2/1002a17b-97ad-4d35-a466-74852d1c6c61.jpg?ci_seal=4b9c7fa2b22526c15fb0cebe29f1a113739c534e",
        "display": true
      },
      "contactLogo": {
        "logoUrl": null,
        "display": false
      }
    },
    "contactForm": {
      "contactCard": {
        "title": "GRAND LYON IMMOBILIER",
        "subtitle": "Lola Mallin",
        "phoneNumbers": [
          "+33787892946 / 0981689689"
        ],
        "isPrivateOwner": false,
        "logoUrl": "https://mms.seloger.com/1/0/0/2/1002a17b-97ad-4d35-a466-74852d1c6c61.jpg?ci_seal=4b9c7fa2b22526c15fb0cebe29f1a113739c534e"
      },
      "displayOwnerFlag": true,
      "subjectLabel": "Votre message à Lola Mallin",
      "shouldSendLeadValue": true
    },
    "mobilePhones": {
      "title": "GRAND LYON IMMOBILIER",
      "subtitle": "GRAND LYON IMMOBILIER",
      "phoneNumbers": [
        "+33787892946 / 0981689689"
      ],
      "logoUrl": null,
      "isPrivateOwner": false
    },
    "provider": {
      "intermediaryCard": {
        "title": "GRAND LYON IMMOBILIER",
        "subtitle": "Agence professionnelle",
        "display": true,
        "logoUrl": "https://mms.seloger.com/1/0/0/2/1002a17b-97ad-4d35-a466-74852d1c6c61.jpg?ci_seal=4b9c7fa2b22526c15fb0cebe29f1a113739c534e",
        "logoHref": "https://www.seloger.com/professionnels/agences-immobilieres/lyon-6eme-arrondissement-69006/agence-29420/"
      },
      "contactCard": {
        "title": "Lola Mallin",
        "subtitle": "Votre contact",
        "display": true,
        "logoUrl": null
      },
      "isPrivateOwner": false,
      "profileUrl": "https://www.seloger.com/professionnels/agences-immobilieres/lyon-6eme-arrondissement-69006/agence-29420/",
      "imprintUrl": null,
      "feeUrl": "http://vd.seloger.com/files/2/7/z/r/27zr6k9mdvvhozgrj4r9vqa5maj08uzc3teixlwcg/Honoraires+GLI.pdf",
      "agencyLegalInformations": [
        "SARL Grand Lyon Immobilier au capital de 3 000 €",
        "Garantie financière Galian pour un montant de 120 000 €",
        "<b>Siège:</b> 3 Rue Henri IV, 69002 Lyon",
        "<b>RCS:</b> LYON 824926638",
        "<b>SIRET:</b> 82492663800027"
      ],
      "publisherType": "AGENCY",
      "displayLinks": true,
      "address": "25 Rue Vauban Lyon, 69006 Lyon 6ème",
      "phoneNumbers": [
        "+33787892946 / 0981689689"
      ]
    },
    "confirmationPage": {
      "isFinanceOfferButtonEnabled": false
    }
  },
  "tracking": {
    "av_category": "classified",
    "av_initiative": "wl_cdp",
    "av_environment": "live",
    "av_estate_type_global": "av_2",
    "av_distribution_type_global": "1",
    "av_client_type": "pro",
    "av_language": "fr",
    "av_zip_code": "69004",
    "av_city": "Lyon",
    "av_items": [
      {
        "index": 0,
        "name": "classified",
        "list_name": "classified_detail",
        "id": "25PS1X2U8A7W",
        "price": 950,
        "estate_type": "av_2",
        "distribution_type": "1",
        "country": "France",
        "city": "Lyon",
        "region": "Auvergne-Rhône-Alpes",
        "province": "Rhône",
        "zip_code": "69004",
        "legacy_id": "255838605",
        "product_type": "standard",
        "client_id": "RC-019240"
      }
    ]
  },
  "legacyTracking": {
    "site": "SL",
    "pagename": "detail",
    "environment": "prod",
    "language": "fr",
    "temp_variable_1": "WL",
    "products": [
      {
        "client_id": "178480",
        "client_type": "pro",
        "distribution_type": "1",
        "estate_postalcode": "69004",
        "estate_type": 1,
        "id": "255838605",
        "id_duo": 255838605,
        "id_solo": 255838605,
        "list_name": "detail",
        "media": 0,
        "nb_bedrooms": 1,
        "nb_rooms": 2,
        "parent_site": "SL",
        "photos_nb": 6,
        "position": 0,
        "price": 950,
        "product_geolocation": "localisation_city",
        "product_type": "estate",
        "product_variant": "classified",
        "space": 25.09
      }
    ]
  },
  "advertising": {
    "slots_config": [
      {
        "id": "div-gam-ad-desktop-top-banner",
        "adUnit": "/199043128/360-seloger/location/general/page-de-detail/leaderboard",
        "size": [
          728,
          90
        ],
        "specificTargeting": {
          "pos": "leaderboard"
        },
        "device": "desktop"
      },
      {
        "id": "ad-medium-rectangle-1",
        "adUnit": "/199043128/360-seloger/location/general/page-de-detail/pave-haut",
        "size": [
          [
            300,
            250
          ],
          "fluid"
        ],
        "specificTargeting": {
          "pos": "pave-haut"
        },
        "device": "desktop"
      },
      {
        "id": "ad-medium-rectangle-2",
        "adUnit": "/199043128/360-seloger/location/general/page-de-detail/pave-bas",
        "size": [
          [
            300,
            250
          ],
          "fluid"
        ],
        "specificTargeting": {
          "pos": "pave-bas"
        },
        "device": "desktop"
      },
      {
        "id": "ad-masonry",
        "adUnit": "/199043128/360-seloger/location/general/page-de-detail/image-galerie",
        "size": [
          [
            624,
            468
          ],
          [
            300,
            250
          ]
        ],
        "specificTargeting": {
          "pos": "image-galerie"
        },
        "device": "desktop"
      },
      {
        "id": "ad-carousel",
        "adUnit": "/199043128/360-seloger/location/general/page-de-detail/pave-carrousel",
        "size": [
          [
            624,
            468
          ],
          [
            300,
            250
          ]
        ],
        "specificTargeting": {
          "pos": "pave-carrousel"
        },
        "device": "desktop"
      },
      {
        "id": "ad-banner-mobile",
        "adUnit": "/199043128/360-seloger/location/general/page-de-detail/banniere-mobile",
        "size": [
          [
            320,
            50
          ],
          [
            320,
            100
          ],
          [
            320,
            150
          ]
        ],
        "specificTargeting": {
          "pos": "banniere-mobile"
        },
        "device": "mobile"
      },
      {
        "id": "ad-masonry",
        "adUnit": "/199043128/360-seloger/location/general/page-de-detail/image-galerie",
        "size": [
          300,
          250
        ],
        "specificTargeting": {
          "pos": "image-galerie"
        },
        "device": "mobile"
      },
      {
        "id": "ad-carousel",
        "adUnit": "/199043128/360-seloger/location/general/page-de-detail/pave-carrousel",
        "size": [
          300,
          250
        ],
        "specificTargeting": {
          "pos": "pave-carrousel"
        },
        "device": "mobile"
      },
      {
        "id": "rental-link",
        "adUnit": "/199043128/360-seloger/location/general/page-de-detail/lien",
        "size": "fluid",
        "specificTargeting": {
          "pos": "Lien"
        },
        "device": "all"
      },
      {
        "id": "partnerbox-1-commercial",
        "adUnit": "/199043128/360-seloger/location/general/page-de-detail/native1",
        "size": "fluid",
        "specificTargeting": {
          "pos": "native1"
        },
        "device": "all"
      },
      {
        "id": "partnerbox-2-commercial",
        "adUnit": "/199043128/360-seloger/location/general/page-de-detail/native2",
        "size": "fluid",
        "specificTargeting": {
          "pos": "native2"
        },
        "device": "all"
      },
      {
        "id": "partnerbox-3-tools-and-service",
        "adUnit": "/199043128/360-seloger/location/general/page-de-detail/native3",
        "size": "fluid",
        "specificTargeting": {
          "pos": "native3"
        },
        "device": "all"
      },
      {
        "id": "partnerbox-4-tools-and-service",
        "adUnit": "/199043128/360-seloger/location/general/page-de-detail/native4",
        "size": "fluid",
        "specificTargeting": {
          "pos": "native4"
        },
        "device": "all"
      },
      {
        "id": "partnerbox-5-tools-and-service",
        "adUnit": "/199043128/360-seloger/location/general/page-de-detail/native5",
        "size": "fluid",
        "specificTargeting": {
          "pos": "native5"
        },
        "device": "all"
      }
    ],
    "tracking_config": {
      "localite": "69123",
      "cp": "69004",
      "geodp": "69",
      "pays": "250",
      "idtt": "1",
      "idtypebien": "1",
      "naturebien": "1",
      "idtiers": "255838605",
      "prix": 1000,
      "nb_pieces": 2,
      "nb_chambres": 1,
      "surface": 25.09,
      "commodites": [
        "Chauffage-individuel",
        "Cuisine-équipée",
        "sansVisAVis",
        "Sejour"
      ],
      "mensualitefinance": 0,
      "si_parking": 0
    }
  },
  "seo": {
    "breadcrumb": {
      "type": "cdp-breadcrumb",
      "name": "breadcrumb",
      "title": "cdp-breadcrumb",
      "slug": "cdp-breadcrumb",
      "links": [
        {
          "order": 1,
          "url": "https://www.seloger.com/",
          "label": "Immobilier",
          "hoverLabel": "Immobilier",
          "serpKey": ""
        },
        {
          "order": 2,
          "url": "https://www.seloger.com/immobilier/pays/locations/bien-appartement/france.htm",
          "label": "Appartements à louer France",
          "hoverLabel": "Appartements à louer France",
          "serpKey": ""
        },
        {
          "order": 3,
          "url": "https://www.seloger.com/immobilier/locations/bien-appartement/rhone-alpes.htm",
          "label": "Appartements à louer Auvergne-Rhône-Alpes",
          "hoverLabel": "Appartements à louer Auvergne-Rhône-Alpes",
          "serpKey": ""
        },
        {
          "order": 4,
          "url": "https://www.seloger.com/immobilier/locations/69/bien-appartement/",
          "label": "Appartements à louer Rhône 69",
          "hoverLabel": "Appartements à louer Rhône 69",
          "serpKey": ""
        },
        {
          "order": 5,
          "url": "https://www.seloger.com/immobilier/locations/immo-lyon-4eme-69/bien-appartement/",
          "label": "Appartements à louer Lyon 4ème arrondissement 69004",
          "hoverLabel": "Appartements à louer Lyon 4ème arrondissement 69004",
          "serpKey": ""
        },
        {
          "order": 100,
          "url": "",
          "label": "Annonce",
          "hoverLabel": "Annonce",
          "serpKey": ""
        }
      ]
    },
    "headInfo": {
      "title": "Appartement à louer T2/F2 25.09 m² 950 € Lyon (69004)",
      "titleWithCount": "",
      "description": "Appartement à louer T2/F2 25.09 m² 950 € Lyon (69004)",
      "canonical": "https://www.seloger.com/annonces/locations/appartement/lyon-4eme-69/255838605.htm",
      "robots": "index, follow, max-snippet:-1",
      "icons": [
        {
          "relation": "shortcut icon",
          "link": "https://www.seloger.com/favicon.ico",
          "type": "image/ico"
        }
      ],
      "openGraphs": [
        {
          "property": "locale",
          "content": "fr_FR"
        },
        {
          "property": "url",
          "content": "https://www.seloger.com/annonces/locations/appartement/lyon-4eme-69/255838605.htm"
        },
        {
          "property": "type",
          "content": "website"
        },
        {
          "property": "site_name",
          "content": "SeLoger"
        },
        {
          "property": "title",
          "content": "Appartement à louer T2/F2 25.09 m² 950 € Lyon (69004)"
        },
        {
          "property": "description",
          "content": "Appartement à louer T2/F2 25.09 m² 950 € Lyon (69004)"
        },
        {
          "property": "image",
          "content": "https://mms.seloger.com/7/5/d/8/75d8e58c-a75f-4118-ac32-bab798128030.jpg?ci_seal=ffb0d1fa81fd3a19f810f35f0925991effea2c84"
        }
      ],
      "socials": [
        {
          "name": "twitter:card",
          "content": "Appartement à louer T2/F2 25.09 m² 950 € Lyon (69004)"
        },
        {
          "name": "twitter:url",
          "content": "https://www.seloger.com/annonces/locations/appartement/lyon-4eme-69/255838605.htm"
        },
        {
          "name": "twitter:site",
          "content": "@seloger"
        },
        {
          "name": "twitter:title",
          "content": "Appartement à louer T2/F2 25.09 m² 950 € Lyon (69004)"
        },
        {
          "name": "twitter:description",
          "content": "Appartement à louer T2/F2 25.09 m² 950 € Lyon (69004)"
        },
        {
          "name": "twitter:image",
          "content": "https://mms.seloger.com/7/5/d/8/75d8e58c-a75f-4118-ac32-bab798128030.jpg?ci_seal=ffb0d1fa81fd3a19f810f35f0925991effea2c84"
        }
      ],
      "structuredData": [
        [
          {
            "type": "@context",
            "content": "https://schema.org"
          },
          {
            "type": "@type",
            "content": "Organization"
          },
          {
            "type": "name",
            "content": "SeLoger"
          },
          {
            "type": "address",
            "content": "2 Rue des Italiens, 75009 Paris"
          },
          {
            "type": "telephone",
            "content": "01 53 38 28 00"
          },
          {
            "type": "url",
            "content": "https://www.seloger.com/"
          },
          {
            "type": "logo",
            "content": "https://static-seloger.com/commons/header/logo_header.svg"
          }
        ],
        [
          {
            "type": "@context",
            "content": "https://schema.org"
          },
          {
            "type": "@type",
            "content": "RealEstateListing"
          },
          {
            "type": "datePosted",
            "content": ""
          },
          {
            "type": "description",
            "content": "Appartement à louer T2/F2 25.09 m² 950 € Lyon (69004)"
          },
          {
            "type": "name",
            "content": "Appartement à louer T2/F2 25.09 m² 950 € Lyon (69004)"
          }
        ]
      ],
      "breadcrumb": [
        {
          "order": 1,
          "url": "https://www.seloger.com/",
          "label": "Immobilier",
          "hoverLabel": "Immobilier",
          "serpKey": ""
        },
        {
          "order": 2,
          "url": "https://www.seloger.com/immobilier/pays/locations/bien-appartement/france.htm",
          "label": "Appartements à louer France",
          "hoverLabel": "Appartements à louer France",
          "serpKey": ""
        },
        {
          "order": 3,
          "url": "https://www.seloger.com/immobilier/locations/bien-appartement/rhone-alpes.htm",
          "label": "Appartements à louer Auvergne-Rhône-Alpes",
          "hoverLabel": "Appartements à louer Auvergne-Rhône-Alpes",
          "serpKey": ""
        },
        {
          "order": 4,
          "url": "https://www.seloger.com/immobilier/locations/69/bien-appartement/",
          "label": "Appartements à louer Rhône 69",
          "hoverLabel": "Appartements à louer Rhône 69",
          "serpKey": ""
        },
        {
          "order": 5,
          "url": "https://www.seloger.com/immobilier/locations/immo-lyon-4eme-69/bien-appartement/",
          "label": "Appartements à louer Lyon 4ème arrondissement 69004",
          "hoverLabel": "Appartements à louer Lyon 4ème arrondissement 69004",
          "serpKey": ""
        }
      ],
      "redirectUrl": "https://www.seloger.com/annonces/locations/appartement/lyon-4eme-69/255838605.htm"
    }
  },
  "farbwelt": {
    "color": "#f07030",
    "textColor": "dark",
    "providerName": "GRAND LYON IMMOBILIER",
    "logo": {
      "src": "https://mms.seloger.com/1/0/0/2/1002a17b-97ad-4d35-a466-74852d1c6c61.jpg?ci_seal=4b9c7fa2b22526c15fb0cebe29f1a113739c534e",
      "alt": "logo-RC-019240",
      "extension": ""
    },
    "teasers": [
      {
        "type": "MediumRectangleTop",
        "image": {
          "src": "https://cdnihddipa.cloudimg.io/9/7/e/b/97eba25a-6a6f-4760-bc4f-29542455e12e.png?ci_eqs=&ci_seal=cb5e8ae220585d9dee5483d1ff0a3b3b258e48b9",
          "alt": "MediumRectangleTop"
        },
        "linkTarget": {
          "href": "https://www.seloger.com/professionnels/agences-immobilieres/lyon-6eme-arrondissement-69006/agence-29420/",
          "isExternal": false
        }
      },
      {
        "type": "MediumRectangleBottom",
        "image": {
          "src": "https://cdnihddipa.cloudimg.io/9/7/e/b/97eba25a-6a6f-4760-bc4f-29542455e12e.png?ci_eqs=&ci_seal=cb5e8ae220585d9dee5483d1ff0a3b3b258e48b9",
          "alt": "MediumRectangleBottom"
        },
        "linkTarget": {
          "href": "https://www.seloger.com/professionnels/agences-immobilieres/lyon-6eme-arrondissement-69006/agence-29420/",
          "isExternal": false
        }
      },
      {
        "type": "MobileBanner",
        "image": {
          "src": "https://cdnihddipa.cloudimg.io/8/f/e/2/8fe2ebd8-2601-4376-a27c-4b04be3163ab.png?ci_eqs=&ci_seal=bad0407f3bf618ffd0d0a84ca037b0d91b33fdad",
          "alt": "MediumRectangleTop"
        },
        "linkTarget": {
          "href": "https://www.seloger.com/professionnels/agences-immobilieres/lyon-6eme-arrondissement-69006/agence-29420/",
          "isExternal": false
        }
      }
    ]
  },
  "defaultBackToSearch": "distributionTypes=Rent&estateTypes=Apartment&locations=AD09FR20&priceMax=1140&priceMin=760",
  "tags": {
    "isExclusive": false,
    "has3DVisit": false,
    "hasBrokerageFee": false,
    "isNew": true,
    "isHdExclusive": false
  },
  "rawData": {
    "distributionType": "RENT",
    "propertyType": "APARTMENT",
    "geoIdHierarchy": [
      {
        "id": "AD09FR20",
        "typeKey": "AD09"
      },
      {
        "id": "AD08FR28808",
        "typeKey": "AD08"
      },
      {
        "id": "AD06FR70",
        "typeKey": "AD06"
      },
      {
        "id": "AD04FR31",
        "typeKey": "AD04"
      },
      {
        "id": "AD03FR2",
        "typeKey": "AD03"
      },
      {
        "id": "AD02FR1",
        "typeKey": "AD02"
      }
    ],
    "distributionSubType": {
      "rent": "CLASSIC"
    }
  },
  "cps": "25PS1X2U8A7W"
}