{
  "brand": "seloger",
  "id": "25XEFK4IM5RK",
  "metadata": {
    "legacyId": "256075137",
    "creationDate": "2025-12-08T14:19:00Z",
    "updateDate": "2025-12-08T14:21:15.148Z",
    "status": {
      "status": true,
      "enrichments": {
        "contactSettings": false,
        "geo": false,
        "intermediary": false,
        "media": false,
        "onlineId": false
      }
    },
    "isNewBuildProject": false
  },
  "sections": {
    "location": {
      "address": {
        "country": "FRA",
        "city": "Lyon 3ème",
        "zipCode": "69003",
        "district": "Montchat"
      },
      "isAddressPublished": false,
      "geometry": {
        "type": "MultiPolygon",
        "coordinates": [
          [
            [
              [
                4.88587,
                45.74542
              ],
              [
                4.88681,
                45.74542
              ],
              [
                4.8877,
                45.7454
              ],
              [
                4.88765,
                45.74571
              ],
              [
                4.88763,
                45.74582
              ],
              [
                4.88872,
                45.74548
              ],
              [
                4.889,
                45.7454
              ],
              [
                4.88912,
                45.74536
              ],
              [
                4.88957,
                45.74522
              ],
              [
                4.89055,
                45.74491
              ],
              [
                4.89113,
                45.74473
              ],
              [
                4.89197,
                45.74446
              ],
              [
                4.8923,
                45.74437
              ],
              [
                4.89246,
                45.74431
              ],
              [
                4.89249,
                45.7443
              ],
              [
                4.89341,
                45.74402
              ],
              [
                4.89362,
                45.74397
              ],
              [
                4.89386,
                45.74389
              ],
              [
                4.89393,
                45.74386
              ],
              [
                4.89417,
                45.74379
              ],
              [
                4.89428,
                45.74376
              ],
              [
                4.89437,
                45.74371
              ],
              [
                4.89443,
                45.74366
              ],
              [
                4.89446,
                45.74365
              ],
              [
                4.89458,
                45.74359
              ],
              [
                4.89463,
                45.7436
              ],
              [
                4.89473,
                45.74364
              ],
              [
                4.89486,
                45.74378
              ],
              [
                4.89477,
                45.74361
              ],
              [
                4.89464,
                45.74344
              ],
              [
                4.89455,
                45.74335
              ],
              [
                4.89451,
                45.74331
              ],
              [
                4.89435,
                45.74308
              ],
              [
                4.89388,
                45.74222
              ],
              [
                4.89384,
                45.74215
              ],
              [
                4.89384,
                45.74213
              ],
              [
                4.89371,
                45.74191
              ],
              [
                4.89366,
                45.74182
              ],
              [
                4.89338,
                45.7413
              ],
              [
                4.89312,
                45.7408
              ],
              [
                4.8929,
                45.7404
              ],
              [
                4.89271,
                45.74003
              ],
              [
                4.89236,
                45.73983
              ],
              [
                4.89206,
                45.7396
              ],
              [
                4.89204,
                45.73956
              ],
              [
                4.89194,
                45.73943
              ],
              [
                4.89189,
                45.73924
              ],
              [
                4.89189,
                45.73921
              ],
              [
                4.89188,
                45.7391
              ],
              [
                4.89161,
                45.7392
              ],
              [
                4.89122,
                45.73933
              ],
              [
                4.89102,
                45.7394
              ],
              [
                4.89029,
                45.73964
              ],
              [
                4.88985,
                45.73979
              ],
              [
                4.88933,
                45.73996
              ],
              [
                4.88841,
                45.74026
              ],
              [
                4.88823,
                45.74032
              ],
              [
                4.88689,
                45.74076
              ],
              [
                4.88557,
                45.7412
              ],
              [
                4.88519,
                45.74131
              ],
              [
                4.88523,
                45.74153
              ],
              [
                4.88526,
                45.74176
              ],
              [
                4.88526,
                45.74179
              ],
              [
                4.88528,
                45.74203
              ],
              [
                4.88533,
                45.74243
              ],
              [
                4.88537,
                45.74273
              ],
              [
                4.88546,
                45.7433
              ],
              [
                4.88549,
                45.74353
              ],
              [
                4.8855,
                45.74362
              ],
              [
                4.88552,
                45.74385
              ],
              [
                4.88556,
                45.74403
              ],
              [
                4.88564,
                45.7446
              ],
              [
                4.88565,
                45.74475
              ],
              [
                4.88567,
                45.74483
              ],
              [
                4.8857,
                45.74512
              ],
              [
                4.88572,
                45.74518
              ],
              [
                4.88578,
                45.7453
              ],
              [
                4.88587,
                45.74542
              ]
            ]
          ]
        ]
      }
    },
    "description": {
      "description": "iad France - Carine Pignard vous propose: Appartement Meublé de 3 pièces – Résidence de Standing “Claire” – Avenue Rockefeller\r\n\r\nDécouvrez cet appartement meublé de 93,77 m² situé dans la prestigieuse résidence Claire, au cOEur de l'Avenue Rockefeller. La résidence offre un cadre de vie sécurisé et agréable, avec gardien, parking fermé, libre et sécurisé, et un environnement calme à proximité immédiate des transports, commerces, universités et hôpitaux.\r\nDescription de l'appartement :\r\nDeux chambres confortables, grande pièce de vie lumineuse regroupant salon et salle à manger, avec accès direct sur un balcon, cuisine aménagée et entièrement équipée, salle de douche moderne et WC séparé. Nombreux rangements dans le dégagement\r\n\r\nRésidence de standing parfaitement entretenue, gardien sur place, parking fermé, libre et sécurisé\r\n\r\nChauffage, eau et charges générales inclus dans les provisions pour charges.\r\nTransports à proximité immédiate : Tram, Métro D, nombreux bus.\r\nCommerces, universités et hôpitaux accessibles à pied.\r\n\r\nModalités de visite\r\n\r\nLes visites se feront uniquement après réception d'un dossier complet sur Zelok.\r\nN'hésitez pas à me contacter afin que je puisse vous transmettre le lien pour déposer votre dossier.\r\n\r\nÉtat des lieux, facturation : 3 euros / m²\r\n\r\nInformation d'affichage énergétique sur ce bien : classe ENERGIE D indice 239 et classe CLIMAT C indice 21. Les informations sur les risques auxquels ce bien est exposé, y compris l'obligation légale de débroussaillement, sont disponibles sur le site Géorisques : \r\nLa présente annonce immobilière a été rédigée sous la responsabilité éditoriale de Mme Carine Pignard mandataire indépendant en immobilier (sans détention de fonds), agent commercial de la SAS I@D France immatriculé au RSAC de LYON sous le numéro 905279444, titulaire de la carte de démarchage immobilier pour le compte de la société I@D France SAS. Location meublée. Montant du loyer mensuel charges comprises : 1390.00 euros / mois. Provision mensuelle avec récupération annuelle : 190.00 euros / mois. Zone soumise à encadrement : oui. Montant du loyer de base : 1153.00 euros / mois. Montant du loyer de référence majoré : 1200.00 euros / mois. Dépôt de garantie : 2400 euros. Honoraires TTC à la charge du locataire: 643 euros (soit 6 euros/m²).",
      "texts": [
        {
          "text": "iad France - Carine Pignard vous propose: Appartement Meublé de 3 pièces – Résidence de Standing “Claire” – Avenue Rockefeller\r\n\r\nDécouvrez cet appartement meublé de 93,77 m² situé dans la prestigieuse résidence Claire, au cOEur de l'Avenue Rockefeller. La résidence offre un cadre de vie sécurisé et agréable, avec gardien, parking fermé, libre et sécurisé, et un environnement calme à proximité immédiate des transports, commerces, universités et hôpitaux.\r\nDescription de l'appartement :\r\nDeux chambres confortables, grande pièce de vie lumineuse regroupant salon et salle à manger, avec accès direct sur un balcon, cuisine aménagée et entièrement équipée, salle de douche moderne et WC séparé. Nombreux rangements dans le dégagement\r\n\r\nRésidence de standing parfaitement entretenue, gardien sur place, parking fermé, libre et sécurisé\r\n\r\nChauffage, eau et charges générales inclus dans les provisions pour charges.\r\nTransports à proximité immédiate : Tram, Métro D, nombreux bus.\r\nCommerces, universités et hôpitaux accessibles à pied.\r\n\r\nModalités de visite\r\n\r\nLes visites se feront uniquement après réception d'un dossier complet sur Zelok.\r\nN'hésitez pas à me contacter afin que je puisse vous transmettre le lien pour déposer votre dossier.\r\n\r\nÉtat des lieux, facturation : 3 euros / m²\r\n\r\nInformation d'affichage énergétique sur ce bien : classe ENERGIE D indice 239 et classe CLIMAT C indice 21. Les informations sur les risques auxquels ce bien est exposé, y compris l'obligation légale de débroussaillement, sont disponibles sur le site Géorisques : \r\nLa présente annonce immobilière a été rédigée sous la responsabilité éditoriale de Mme Carine Pignard mandataire indépendant en immobilier (sans détention de fonds), agent commercial de la SAS I@D France immatriculé au RSAC de LYON sous le numéro 905279444, titulaire de la carte de démarchage immobilier pour le compte de la société I@D France SAS. Location meublée. Montant du loyer mensuel charges comprises : 1390.00 euros / mois. Provision mensuelle avec récupération annuelle : 190.00 euros / mois. Zone soumise à encadrement : oui. Montant du loyer de base : 1153.00 euros / mois. Montant du loyer de référence majoré : 1200.00 euros / mois. Dépôt de garantie : 2400 euros. Honoraires TTC à la charge du locataire: 643 euros (soit 6 euros/m²)."
        }
      ],
      "headline": "Location Appartement 3 pièces"
    },
    "hardFacts": {
      "title": "Appartement à louer",
      "keyfacts": [
        "3 pièces",
        "2 chambres",
        "94 m²",
        "Étage 1/8"
      ],
      "facts": [
        {
          "type": "numberOfRooms",
          "value": "3 pièces",
          "splitValue": "3",
          "label": "pièces"
        },
        {
          "type": "numberOfBedrooms",
          "value": "2 chambres",
          "splitValue": "2",
          "label": "chambres"
        },
        {
          "type": "livingSpace",
          "value": "94 m²",
          "splitValue": "94",
          "label": "m²"
        },
        {
          "type": "numberOfFloors",
          "value": "Étage 1/8",
          "splitValue": "Étage",
          "label": "1/8"
        }
      ],
      "price": {
        "value": "1 390 €",
        "formatted": "1 390 €/mois",
        "modifiers": "/mois",
        "unitPostfix": {
          "unitTime": "/mois"
        },
        "additionalInformation": "charges comprises",
        "addition": {
          "value": "cc",
          "priceLabelDesc": "charges comprises"
        },
        "financialLink": {
          "href": "https://www.nextories.com/partner/landing/seloger?utm_source=seloger&utm_medium=nativelien-prix-loc-2&utm_campaign=nativelienprix-pagesdetails-seloger-location2",
          "label": "Demander un financement",
          "partnerName": "NEXTORIES_RESERVEZ"
        },
        "ariaLabel": "1390 €",
        "chargesLabel": "cc"
      }
    },
    "energy": {
      "features": [
        {
          "type": "yearOfConstruction",
          "label": "Année de construction",
          "value": "1963"
        },
        {
          "type": "heatingSystem",
          "label": "Type de chauffage",
          "value": "Chauffage central"
        },
        {
          "type": "energySource",
          "label": "Sources d'énergie",
          "value": "Électrique"
        }
      ],
      "certificates": [
        {
          "key": "c263c086-73ac-42e0-97a7-6aa5167de113",
          "features": [
            {
              "type": "minMaxEstimation",
              "label": "Estimation de la facture énergétique",
              "value": "entre 1780 et 2470 €/an"
            },
            {
              "type": "nameOfCertificate",
              "label": "Diagnostic réalisé",
              "value": "Après le 1er juillet 2021"
            },
            {
              "type": "estimationDescription",
              "label": "estimationDescription",
              "value": "Montant estimé des dépenses annuelles d'énergie pour un usage standard: entre 1780 et 2470 € par an. Prix moyens des énergies indexés au 31/12/2022 (abonnement compris)."
            }
          ],
          "scales": [
            {
              "key": "140ddd4e-712a-44b6-9543-4e96ba7c0613",
              "efficiencyClass": {
                "index": 3,
                "rating": "D"
              },
              "values": [
                {
                  "value": "239 kWh/m².an",
                  "label": "Consommation (énergie primaire)"
                },
                {
                  "value": "21 kg CO₂/m².an",
                  "label": "Émissions"
                }
              ],
              "name": "Diagnostic de performance énergétique (DPE)",
              "segments": [
                {
                  "label": "A",
                  "value": ""
                },
                {
                  "label": "B",
                  "value": ""
                },
                {
                  "label": "C",
                  "value": ""
                },
                {
                  "label": "D",
                  "value": ""
                },
                {
                  "label": "E",
                  "value": ""
                },
                {
                  "label": "F",
                  "value": "Passoire énergétique"
                },
                {
                  "label": "G",
                  "value": "Passoire énergétique"
                }
              ],
              "type": "FR_ENERGY_AFTER_2021",
              "ariaLabel": "EfficiencyClass : D avec une plage allant de A à G .La consommation d'énergie est undefined kWhEP/m².an kilowattheures par mètre carré.",
              "displayUnhappyHouseIcon": false
            },
            {
              "key": "48dcd373-d9c1-461d-b9c2-7fe72a1a8e85",
              "efficiencyClass": {
                "index": 2,
                "rating": "C"
              },
              "values": [
                {
                  "value": "21 kg CO₂/m².an",
                  "label": "Émissions"
                }
              ],
              "name": "Indice d'émission de gaz à effet de serre (GES)",
              "segments": [
                {
                  "label": "A",
                  "value": ""
                },
                {
                  "label": "B",
                  "value": ""
                },
                {
                  "label": "C",
                  "value": ""
                },
                {
                  "label": "D",
                  "value": ""
                },
                {
                  "label": "E",
                  "value": ""
                },
                {
                  "label": "F",
                  "value": ""
                },
                {
                  "label": "G",
                  "value": ""
                }
              ],
              "type": "FR_GHG_AFTER_2021",
              "ariaLabel": "EfficiencyClass : C avec une plage allant de A à G .La consommation d'énergie est undefined kWhEP/m².an kilowattheures par mètre carré.",
              "displayUnhappyHouseIcon": false
            }
          ]
        }
      ],
      "hasScales": true
    },
    "key": {
      "keys": [
        {
          "label": "Identifiant",
          "value": "256075137"
        },
        {
          "label": "Référence annonce",
          "value": "1894315"
        }
      ]
    },
    "price": {
      "base": {
        "main": {
          "label": "Loyer charges comprises",
          "value": "1 390 €/mois Loyer charges comprises",
          "ariaLabel": "1390 €/mois Loyer charges comprises"
        },
        "details": [
          {
            "label": "Coûts supplémentaires",
            "value": "190 €/mois",
            "ariaLabel": "190 €"
          },
          {
            "label": "Prix ​​au m²",
            "value": "14,79 €/mois/m²",
            "ariaLabel": "14,79 euros par mètre carré"
          }
        ]
      }
    },
    "features": {
      "preview": [
        {
          "icon": "floors",
          "value": "1er étage/8 étages"
        },
        {
          "icon": "elevator",
          "value": "Ascenseur"
        },
        {
          "icon": "cellar",
          "value": "Pas de cave"
        },
        {
          "icon": "parking-lots",
          "value": "Parking"
        },
        {
          "icon": "balcony",
          "value": "Balcon (Total 16 m²)"
        },
        {
          "icon": "calm",
          "value": "Calme"
        },
        {
          "icon": "furnished",
          "value": "Meublé"
        },
        {
          "icon": "bedroom",
          "value": "2 chambres"
        }
      ],
      "details": {
        "categories": [
          {
            "elements": [
              {
                "icon": "calm",
                "value": "Calme"
              },
              {
                "icon": "furnished",
                "value": "Meublé"
              },
              {
                "icon": "floors",
                "value": "1er étage/8 étages"
              }
            ],
            "title": "Informations générales"
          },
          {
            "elements": [
              {
                "icon": "elevator",
                "value": "Ascenseur"
              }
            ],
            "title": "Accessibilité"
          },
          {
            "elements": [
              {
                "icon": "bedroom",
                "value": "2 chambres"
              },
              {
                "icon": "diningRoomSpace",
                "value": "Salle à manger (total 30 m²)"
              },
              {
                "icon": "cellar",
                "value": "Pas de cave"
              }
            ],
            "title": "Intérieur"
          },
          {
            "elements": [
              {
                "icon": "balcony",
                "value": "Balcon (Total 16 m²)"
              },
              {
                "icon": "parking-lots",
                "value": "Parking"
              }
            ],
            "title": "Extérieur"
          },
          {
            "elements": [
              {
                "icon": "intercom",
                "value": "Interphone"
              },
              {
                "value": "Gardien",
                "icon": "custodian"
              }
            ],
            "title": "Sécurité et services"
          }
        ]
      }
    },
    "gallery": {
      "images": [
        {
          "key": "193bf594-44e1-40c3-b585-9e621e629c1f",
          "url": "https://mms.seloger.com/1/9/3/b/193bf594-44e1-40c3-b585-9e621e629c1f.jpg?ci_seal=9f26e2eaa584a5f8849479c5b1ef08b4824ceefe",
          "alt": "Appartement à louer 1 390 € 3 pièces 2 chambres 94 m² Étage 1/8 Montchat Lyon 3ème 69003",
          "classification": {
            "name": "TERRACE",
            "version": "scene-classification-sagemaker-endpoint-live-1-3-10"
          }
        },
        {
          "key": "78f42837-68a8-4cef-84c8-7573cacd7c49",
          "url": "https://mms.seloger.com/7/8/f/4/78f42837-68a8-4cef-84c8-7573cacd7c49.jpg?ci_seal=77e1eb85e395c4cf4b014291952a319d75f9a426",
          "classification": {
            "name": "TERRACE",
            "version": "scene-classification-sagemaker-endpoint-live-1-3-10"
          }
        },
        {
          "key": "bed3d0d0-056d-42df-b238-52c424507102",
          "url": "https://mms.seloger.com/b/e/d/3/bed3d0d0-056d-42df-b238-52c424507102.jpg?ci_seal=b434b7d33cf11003a323b9bd510554ba0dd200ed",
          "classification": {
            "name": "LIVING_ROOM",
            "version": "scene-classification-sagemaker-endpoint-live-1-3-10"
          }
        },
        {
          "key": "18808ddd-f695-45ca-a2e4-975bbaf1b12f",
          "url": "https://mms.seloger.com/1/8/8/0/18808ddd-f695-45ca-a2e4-975bbaf1b12f.jpg?ci_seal=d20617593ce89d73cefb9c477756062b5a399df7",
          "classification": {
            "name": "LIVING_ROOM",
            "version": "scene-classification-sagemaker-endpoint-live-1-3-10"
          }
        },
        {
          "key": "26d9c96f-c50b-45b1-b38d-6a18a1e7d9be",
          "url": "https://mms.seloger.com/2/6/d/9/26d9c96f-c50b-45b1-b38d-6a18a1e7d9be.jpg?ci_seal=f2ea1364fc69efa65f2db6e9d43d36e22efd073d",
          "classification": {
            "name": "LIVING_ROOM",
            "version": "scene-classification-sagemaker-endpoint-live-1-3-10"
          }
        },
        {
          "key": "cf83ec41-0ea4-4418-87cd-f5e482dd989e",
          "url": "https://mms.seloger.com/c/f/8/3/cf83ec41-0ea4-4418-87cd-f5e482dd989e.jpg?ci_seal=1799692859841dab297664b1fb521b2406dfea72",
          "classification": {
            "name": "BEDROOM",
            "version": "scene-classification-sagemaker-endpoint-live-1-3-10"
          }
        },
        {
          "key": "93ae3ddb-9a82-4374-8b47-5195190a2909",
          "url": "https://mms.seloger.com/9/3/a/e/93ae3ddb-9a82-4374-8b47-5195190a2909.jpg?ci_seal=724dcd6531db0e82c8c6f303626ead05fae0d8a8",
          "classification": {
            "name": "BEDROOM",
            "version": "scene-classification-sagemaker-endpoint-live-1-3-10"
          }
        },
        {
          "key": "5198788e-9a92-41aa-8d08-ab5ce3d57eb1",
          "url": "https://mms.seloger.com/5/1/9/8/5198788e-9a92-41aa-8d08-ab5ce3d57eb1.jpg?ci_seal=f612cbf63e9d5bf7908fd316b3645b8a2e380673",
          "classification": {
            "name": "BEDROOM",
            "version": "scene-classification-sagemaker-endpoint-live-1-3-10"
          }
        },
        {
          "key": "60e9f9a6-c3f3-4b2b-80a7-9a4217a71225",
          "url": "https://mms.seloger.com/6/0/e/9/60e9f9a6-c3f3-4b2b-80a7-9a4217a71225.jpg?ci_seal=b65fde2010aff7ebfa105e0cbe99c9293717fe17",
          "classification": {
            "name": "BEDROOM",
            "version": "scene-classification-sagemaker-endpoint-live-1-3-10"
          }
        }
      ]
    },
    "documents": {
      "display": false,
      "files": []
    },
    "enrichedMedia": {
      "medias": []
    },
    "mortgage": {
      "brand": "seloger",
      "id": "256075137",
      "federalStateGeoId": "AD04FR31",
      "zip": "69003",
      "city": "Lyon 3ème",
      "country": "FRA",
      "region": "Auvergne-Rhône-Alpes",
      "showRentLabel": true,
      "showMonthlyRateLabel": false,
      "price": 0,
      "prov": 0,
      "monthlyAmount": 0,
      "formattedMonthlyAmount": "0"
    },
    "partnerAd": {
      "showPartnerAd": false
    },
    "sellerLeadLink": {},
    "priceComparison": {
      "data": {
        "value": 17.42,
        "accuracy": 4,
        "high": "25,95",
        "low": "13,10"
      },
      "markerPosition": 13,
      "hasMainPrice": true,
      "isSale": false,
      "pricePerSqm": "14,79",
      "legalText": "Le prix au m2 est automatiquement calculé par Se Loger en fonction du prix de vente et du nombre de m2 du bien. La comparaison est réalisée à partir des informations relatives au prix du marché sur le même secteur dont dispose Se Loger. Cette information ne préjuge en aucun cas de l'évaluation du bien, qui dépend de son état, ses caractéristiques et de sa localisation."
    },
    "mainDescription": {
      "headline": "Location Appartement 3 pièces",
      "description": "iad France - Carine Pignard vous propose: Appartement Meublé de 3 pièces – Résidence de Standing “Claire” – Avenue Rockefeller\r\n\r\nDécouvrez cet appartement meublé de 93,77 m² situé dans la prestigieuse résidence Claire, au cOEur de l'Avenue Rockefeller. La résidence offre un cadre de vie sécurisé et agréable, avec gardien, parking fermé, libre et sécurisé, et un environnement calme à proximité immédiate des transports, commerces, universités et hôpitaux.\r\nDescription de l'appartement :\r\nDeux chambres confortables, grande pièce de vie lumineuse regroupant salon et salle à manger, avec accès direct sur un balcon, cuisine aménagée et entièrement équipée, salle de douche moderne et WC séparé. Nombreux rangements dans le dégagement\r\n\r\nRésidence de standing parfaitement entretenue, gardien sur place, parking fermé, libre et sécurisé\r\n\r\nChauffage, eau et charges générales inclus dans les provisions pour charges.\r\nTransports à proximité immédiate : Tram, Métro D, nombreux bus.\r\nCommerces, universités et hôpitaux accessibles à pied.\r\n\r\nModalités de visite\r\n\r\nLes visites se feront uniquement après réception d'un dossier complet sur Zelok.\r\nN'hésitez pas à me contacter afin que je puisse vous transmettre le lien pour déposer votre dossier.\r\n\r\nÉtat des lieux, facturation : 3 euros / m²\r\n\r\nInformation d'affichage énergétique sur ce bien : classe ENERGIE D indice 239 et classe CLIMAT C indice 21. Les informations sur les risques auxquels ce bien est exposé, y compris l'obligation légale de débroussaillement, sont disponibles sur le site Géorisques : \r\nLa présente annonce immobilière a été rédigée sous la responsabilité éditoriale de Mme Carine Pignard mandataire indépendant en immobilier (sans détention de fonds), agent commercial de la SAS I@D France immatriculé au RSAC de LYON sous le numéro 905279444, titulaire de la carte de démarchage immobilier pour le compte de la société I@D France SAS. Location meublée. Montant du loyer mensuel charges comprises : 1390.00 euros / mois. Provision mensuelle avec récupération annuelle : 190.00 euros / mois. Zone soumise à encadrement : oui. Montant du loyer de base : 1153.00 euros / mois. Montant du loyer de référence majoré : 1200.00 euros / mois. Dépôt de garantie : 2400 euros. Honoraires TTC à la charge du locataire: 643 euros (soit 6 euros/m²).",
      "metadata": {
        "language": "fr"
      }
    },
    "areaDescription": {
      "headline": "Emplacement"
    },
    "extendedInfoDescription": {
      "headline": "Informations supplémentaires"
    },
    "statistics": {
      "published": "1 jour en ligne",
      "views": "135 vues",
      "saves": "2 favoris"
    }
  },
  "contactSections": {
    "id": "25XEFK4IM5RK",
    "legacyId": "256075137",
    "brand": "seloger",
    "agencyId": "RC-1827978",
    "static": {
      "phoneNumbers": [
        "0632903306"
      ]
    },
    "sticky": {
      "phoneNumbers": [
        "0632903306"
      ]
    },
    "contactCard": {
      "title": "iad France  Carine Pignard",
      "subtitle": "Carine Pignard",
      "phoneNumbers": [
        "0632903306"
      ],
      "isPrivateOwner": false,
      "agencyLogo": {
        "logoUrl": "https://mms.seloger.com/c/9/7/f/c97fc1f3-ef25-4662-895e-a86992742b29.jpg?ci_seal=8339336e442308271d3bb8712e31b622fa79c590",
        "display": true
      },
      "contactLogo": {
        "logoUrl": null,
        "display": false
      }
    },
    "contactForm": {
      "contactCard": {
        "title": "iad France  Carine Pignard",
        "subtitle": "Carine Pignard",
        "phoneNumbers": [
          "0632903306"
        ],
        "isPrivateOwner": false,
        "logoUrl": "https://mms.seloger.com/c/9/7/f/c97fc1f3-ef25-4662-895e-a86992742b29.jpg?ci_seal=8339336e442308271d3bb8712e31b622fa79c590"
      },
      "displayOwnerFlag": true,
      "subjectLabel": "Votre message à Carine Pignard",
      "shouldSendLeadValue": true
    },
    "mobilePhones": {
      "title": "iad France  Carine Pignard",
      "subtitle": "iad France  Carine Pignard",
      "phoneNumbers": [
        "0632903306"
      ],
      "logoUrl": null,
      "isPrivateOwner": false
    },
    "provider": {
      "intermediaryCard": {
        "title": "iad France  Carine Pignard",
        "subtitle": "Agence professionnelle",
        "display": true,
        "logoUrl": "https://mms.seloger.com/c/9/7/f/c97fc1f3-ef25-4662-895e-a86992742b29.jpg?ci_seal=8339336e442308271d3bb8712e31b622fa79c590",
        "logoHref": "https://www.seloger.com/professionnels/agents-commerciaux/saint-priest-69800/agence-113142/"
      },
      "contactCard": {
        "title": "Carine Pignard",
        "subtitle": "Votre contact",
        "display": true,
        "logoUrl": null
      },
      "website": "https://www.iadfrance.fr/fr/conseiller/@carine.pignard??utm_campaign=spring&utm_medium=referral&utm_source=seloger",
      "isPrivateOwner": false,
      "profileUrl": "https://www.seloger.com/professionnels/agents-commerciaux/saint-priest-69800/agence-113142/",
      "imprintUrl": null,
      "feeUrl": "https://bareme.iadfrance.fr/",
      "agencyLegalInformations": [
        "Pignard Carine",
        "<b>RCS:</b> 905279444"
      ],
      "publisherType": "REAL_ESTATE_AGENT",
      "displayLinks": true,
      "address": "69800 SAINT-PRIEST",
      "phoneNumbers": [
        "0632903306"
      ]
    },
    "confirmationPage": {
      "isFinanceOfferButtonEnabled": false
    }
  },
  "tracking": {
    "av_category": "classified",
    "av_initiative": "wl_cdp",
    "av_environment": "live",
    "av_estate_type_global": "av_2",
    "av_distribution_type_global": "1",
    "av_client_type": "pro",
    "av_language": "fr",
    "av_zip_code": "69003",
    "av_city": "Lyon",
    "av_energy_certificate": "D",
    "av_items": [
      {
        "index": 0,
        "name": "classified",
        "list_name": "classified_detail",
        "id": "25XEFK4IM5RK",
        "price": 1390,
        "estate_type": "av_2",
        "distribution_type": "1",
        "country": "France",
        "city": "Lyon",
        "region": "Auvergne-Rhône-Alpes",
        "province": "Rhône",
        "zip_code": "69003",
        "legacy_id": "256075137",
        "product_type": "standard",
        "client_id": "RC-1827978",
        "energy_certificate": "D"
      }
    ]
  },
  "legacyTracking": {
    "site": "SL",
    "pagename": "detail",
    "environment": "prod",
    "language": "fr",
    "temp_variable_1": "WL",
    "products": [
      {
        "client_id": "474597",
        "client_type": "pro",
        "distribution_type": "1",
        "energy_letter": "D",
        "estate_postalcode": "69003",
        "estate_type": 1,
        "id": "256075137",
        "id_duo": 256075137,
        "id_solo": 256075137,
        "list_name": "detail",
        "media": 0,
        "nb_bedrooms": 2,
        "nb_rooms": 3,
        "parent_site": "SL",
        "photos_nb": 9,
        "position": 0,
        "price": 1390,
        "product_geolocation": "localisation_city",
        "product_type": "estate",
        "product_variant": "classified",
        "space": 94,
        "year_of_construction": 1963
      }
    ]
  },
  "advertising": {
    "slots_config": [
      {
        "id": "div-gam-ad-desktop-top-banner",
        "adUnit": "/199043128/360-seloger/location/general/page-de-detail/leaderboard",
        "size": [
          728,
          90
        ],
        "specificTargeting": {
          "pos": "leaderboard"
        },
        "device": "desktop"
      },
      {
        "id": "ad-medium-rectangle-1",
        "adUnit": "/199043128/360-seloger/location/general/page-de-detail/pave-haut",
        "size": [
          [
            300,
            250
          ],
          "fluid"
        ],
        "specificTargeting": {
          "pos": "pave-haut"
        },
        "device": "desktop"
      },
      {
        "id": "ad-medium-rectangle-2",
        "adUnit": "/199043128/360-seloger/location/general/page-de-detail/pave-bas",
        "size": [
          [
            300,
            250
          ],
          "fluid"
        ],
        "specificTargeting": {
          "pos": "pave-bas"
        },
        "device": "desktop"
      },
      {
        "id": "ad-masonry",
        "adUnit": "/199043128/360-seloger/location/general/page-de-detail/image-galerie",
        "size": [
          [
            624,
            468
          ],
          [
            300,
            250
          ]
        ],
        "specificTargeting": {
          "pos": "image-galerie"
        },
        "device": "desktop"
      },
      {
        "id": "ad-carousel",
        "adUnit": "/199043128/360-seloger/location/general/page-de-detail/pave-carrousel",
        "size": [
          [
            624,
            468
          ],
          [
            300,
            250
          ]
        ],
        "specificTargeting": {
          "pos": "pave-carrousel"
        },
        "device": "desktop"
      },
      {
        "id": "ad-banner-mobile",
        "adUnit": "/199043128/360-seloger/location/general/page-de-detail/banniere-mobile",
        "size": [
          [
            320,
            50
          ],
          [
            320,
            100
          ],
          [
            320,
            150
          ]
        ],
        "specificTargeting": {
          "pos": "banniere-mobile"
        },
        "device": "mobile"
      },
      {
        "id": "ad-masonry",
        "adUnit": "/199043128/360-seloger/location/general/page-de-detail/image-galerie",
        "size": [
          300,
          250
        ],
        "specificTargeting": {
          "pos": "image-galerie"
        },
        "device": "mobile"
      },
      {
        "id": "ad-carousel",
        "adUnit": "/199043128/360-seloger/location/general/page-de-detail/pave-carrousel",
        "size": [
          300,
          250
        ],
        "specificTargeting": {
          "pos": "pave-carrousel"
        },
        "device": "mobile"
      },
      {
        "id": "rental-link",
        "adUnit": "/199043128/360-seloger/location/general/page-de-detail/lien",
        "size": "fluid",
        "specificTargeting": {
          "pos": "Lien"
        },
        "device": "all"
      },
      {
        "id": "partnerbox-1-commercial",
        "adUnit": "/199043128/360-seloger/location/general/page-de-detail/native1",
        "size": "fluid",
        "specificTargeting": {
          "pos": "native1"
        },
        "device": "all"
      },
      {
        "id": "partnerbox-2-commercial",
        "adUnit": "/199043128/360-seloger/location/general/page-de-detail/native2",
        "size": "fluid",
        "specificTargeting": {
          "pos": "native2"
        },
        "device": "all"
      },
      {
        "id": "partnerbox-3-tools-and-service",
        "adUnit": "/199043128/360-seloger/location/general/page-de-detail/native3",
        "size": "fluid",
        "specificTargeting": {
          "pos": "native3"
        },
        "device": "all"
      },
      {
        "id": "partnerbox-4-tools-and-service",
        "adUnit": "/199043128/360-seloger/location/general/page-de-detail/native4",
        "size": "fluid",
        "specificTargeting": {
          "pos": "native4"
        },
        "device": "all"
      },
      {
        "id": "partnerbox-5-tools-and-service",
        "adUnit": "/199043128/360-seloger/location/general/page-de-detail/native5",
        "size": "fluid",
        "specificTargeting": {
          "pos": "native5"
        },
        "device": "all"
      }
    ],
    "tracking_config": {
      "localite": "69123",
      "cp": "69003",
      "geodp": "69",
      "pays": "250",
      "idtt": "1",
      "idtypebien": "1",
      "naturebien": "1",
      "idtiers": "256075137",
      "prix": 1400,
      "nb_pieces": 3,
      "nb_chambres": 2,
      "surface": 94,
      "etage": 8,
      "commodites": [
        "ascenseur",
        "balcon",
        "Chauffage-central",
        "Chauffage-electrique",
        "parking%20ouvert",
        "SalleAmanger"
      ],
      "mensualitefinance": 0,
      "si_parking": 1,
      "DPE": "D"
    }
  },
  "seo": {
    "breadcrumb": {
      "type": "cdp-breadcrumb",
      "name": "breadcrumb",
      "title": "cdp-breadcrumb",
      "slug": "cdp-breadcrumb",
      "links": [
        {
          "order": 1,
          "url": "https://www.seloger.com/",
          "label": "Immobilier",
          "hoverLabel": "Immobilier",
          "serpKey": ""
        },
        {
          "order": 2,
          "url": "https://www.seloger.com/immobilier/pays/locations/bien-appartement/france.htm",
          "label": "Appartements à louer France",
          "hoverLabel": "Appartements à louer France",
          "serpKey": ""
        },
        {
          "order": 3,
          "url": "https://www.seloger.com/immobilier/locations/bien-appartement/rhone-alpes.htm",
          "label": "Appartements à louer Auvergne-Rhône-Alpes",
          "hoverLabel": "Appartements à louer Auvergne-Rhône-Alpes",
          "serpKey": ""
        },
        {
          "order": 4,
          "url": "https://www.seloger.com/immobilier/locations/69/bien-appartement/",
          "label": "Appartements à louer Rhône 69",
          "hoverLabel": "Appartements à louer Rhône 69",
          "serpKey": ""
        },
        {
          "order": 5,
          "url": "https://www.seloger.com/immobilier/locations/immo-lyon-3eme-69/bien-appartement/",
          "label": "Appartements à louer Lyon 3ème arrondissement 69003",
          "hoverLabel": "Appartements à louer Lyon 3ème arrondissement 69003",
          "serpKey": ""
        },
        {
          "order": 100,
          "url": "",
          "label": "Annonce",
          "hoverLabel": "Annonce",
          "serpKey": ""
        }
      ]
    },
    "headInfo": {
      "title": "Appartement à louer T3/F3 94 m² 1390 € Montchat Lyon (69003)",
      "titleWithCount": "",
      "description": "Appartement à louer T3/F3 94 m² 1390 € Montchat Lyon (69003)",
      "canonical": "https://www.seloger.com/annonces/locations/appartement/lyon-3eme-69/montchat/256075137.htm",
      "robots": "index, follow, max-snippet:-1",
      "icons": [
        {
          "relation": "shortcut icon",
          "link": "https://www.seloger.com/favicon.ico",
          "type": "image/ico"
        }
      ],
      "openGraphs": [
        {
          "property": "locale",
          "content": "fr_FR"
        },
        {
          "property": "url",
          "content": "https://www.seloger.com/annonces/locations/appartement/lyon-3eme-69/montchat/256075137.htm"
        },
        {
          "property": "type",
          "content": "website"
        },
        {
          "property": "site_name",
          "content": "SeLoger"
        },
        {
          "property": "title",
          "content": "Appartement à louer T3/F3 94 m² 1390 € Montchat Lyon (69003)"
        },
        {
          "property": "description",
          "content": "Appartement à louer T3/F3 94 m² 1390 € Montchat Lyon (69003)"
        },
        {
          "property": "image",
          "content": "https://mms.seloger.com/1/9/3/b/193bf594-44e1-40c3-b585-9e621e629c1f.jpg?ci_seal=9f26e2eaa584a5f8849479c5b1ef08b4824ceefe"
        }
      ],
      "socials": [
        {
          "name": "twitter:card",
          "content": "Appartement à louer T3/F3 94 m² 1390 € Montchat Lyon (69003)"
        },
        {
          "name": "twitter:url",
          "content": "https://www.seloger.com/annonces/locations/appartement/lyon-3eme-69/montchat/256075137.htm"
        },
        {
          "name": "twitter:site",
          "content": "@seloger"
        },
        {
          "name": "twitter:title",
          "content": "Appartement à louer T3/F3 94 m² 1390 € Montchat Lyon (69003)"
        },
        {
          "name": "twitter:description",
          "content": "Appartement à louer T3/F3 94 m² 1390 € Montchat Lyon (69003)"
        },
        {
          "name": "twitter:image",
          "content": "https://mms.seloger.com/1/9/3/b/193bf594-44e1-40c3-b585-9e621e629c1f.jpg?ci_seal=9f26e2eaa584a5f8849479c5b1ef08b4824ceefe"
        }
      ],
      "structuredData": [
        [
          {
            "type": "@context",
            "content": "https://schema.org"
          },
          {
            "type": "@type",
            "content": "Organization"
          },
          {
            "type": "name",
            "content": "SeLoger"
          },
          {
            "type": "address",
            "content": "2 Rue des Italiens, 75009 Paris"
          },
          {
            "type": "telephone",
            "content": "01 53 38 28 00"
          },
          {
            "type": "url",
            "content": "https://www.seloger.com/"
          },
          {
            "type": "logo",
            "content": "https://static-seloger.com/commons/header/logo_header.svg"
          }
        ],
        [
          {
            "type": "@context",
            "content": "https://schema.org"
          },
          {
            "type": "@type",
            "content": "RealEstateListing"
          },
          {
            "type": "datePosted",
            "content": ""
          },
          {
            "type": "description",
            "content": "Appartement à louer T3/F3 94 m² 1390 € Montchat Lyon (69003)"
          },
          {
            "type": "name",
            "content": "Appartement à louer T3/F3 94 m² 1390 € Montchat Lyon (69003)"
          }
        ]
      ],
      "breadcrumb": [
        {
          "order": 1,
          "url": "https://www.seloger.com/",
          "label": "Immobilier",
          "hoverLabel": "Immobilier",
          "serpKey": ""
        },
        {
          "order": 2,
          "url": "https://www.seloger.com/immobilier/pays/locations/bien-appartement/france.htm",
          "label": "Appartements à louer France",
          "hoverLabel": "Appartements à louer France",
          "serpKey": ""
        },
        {
          "order": 3,
          "url": "https://www.seloger.com/immobilier/locations/bien-appartement/rhone-alpes.htm",
          "label": "Appartements à louer Auvergne-Rhône-Alpes",
          "hoverLabel": "Appartements à louer Auvergne-Rhône-Alpes",
          "serpKey": ""
        },
        {
          "order": 4,
          "url": "https://www.seloger.com/immobilier/locations/69/bien-appartement/",
          "label": "Appartements à louer Rhône 69",
          "hoverLabel": "Appartements à louer Rhône 69",
          "serpKey": ""
        },
        {
          "order": 5,
          "url": "https://www.seloger.com/immobilier/locations/immo-lyon-3eme-69/bien-appartement/",
          "label": "Appartements à louer Lyon 3ème arrondissement 69003",
          "hoverLabel": "Appartements à louer Lyon 3ème arrondissement 69003",
          "serpKey": ""
        }
      ],
      "redirectUrl": "https://www.seloger.com/annonces/locations/appartement/lyon-3eme-69/montchat/256075137.htm"
    }
  },
  "defaultBackToSearch": "distributionTypes=Rent&estateTypes=Apartment&locations=NBH2FR9344&priceMax=1668&priceMin=1112",
  "tags": {
    "isExclusive": true,
    "has3DVisit": false,
    "hasBrokerageFee": false,
    "isNew": true,
    "isHdExclusive": false
  },
  "rawData": {
    "distributionType": "RENT",
    "propertyType": "APARTMENT",
    "geoIdHierarchy": [
      {
        "id": "NBH2FR9344",
        "typeKey": "NBH2"
      },
      {
        "id": "AD09FR19",
        "typeKey": "AD09"
      },
      {
        "id": "AD08FR28808",
        "typeKey": "AD08"
      },
      {
        "id": "AD06FR70",
        "typeKey": "AD06"
      },
      {
        "id": "AD04FR31",
        "typeKey": "AD04"
      },
      {
        "id": "AD03FR2",
        "typeKey": "AD03"
      },
      {
        "id": "AD02FR1",
        "typeKey": "AD02"
      }
    ],
    "distributionSubType": {
      "rent": "CLASSIC"
    }
  },
  "cps": "25XEFK4IM5RK"
}