{
  "brand": "seloger",
  "id": "25CIEA6XFL6E",
  "metadata": {
    "legacyId": "256170979",
    "creationDate": "2025-12-09T18:07:00Z",
    "updateDate": "2025-12-09T18:11:13.727Z",
    "status": {
      "status": true,
      "enrichments": {
        "contactSettings": false,
        "geo": false,
        "intermediary": false,
        "media": false,
        "onlineId": false
      }
    },
    "isNewBuildProject": false
  },
  "sections": {
    "location": {
      "address": {
        "country": "FRA",
        "city": "Marseille 9ème",
        "zipCode": "13009",
        "district": "Le Redon"
      },
      "isAddressPublished": true,
      "geometry": {
        "type": "Point",
        "coordinates": [
          5.425391,
          43.248402
        ]
      }
    },
    "description": {
      "description": "SECTEUR - Redon - Agréable appartement Type 2 de 57m² meublé et climatisé avec balcon situé au 1er étage avec ascenseur au 31 rue Nicole Zemmour dans le 9e arrondissement de Marseille. Parking libre dans la résidence fermée et sécurisée. \r\n\r\nCet appartement se compose d'une entrée, d'un grand séjour avec cuisine ouverte entièrement équipée donnant sur une terrasse, une chambre et d'une salle d'eau avec toilettes.\r\n\r\nÀ proximité des arrêts de bus (24/48), du parc de la colline saint Joseph, des commerces et de l'hopital Clairval.\r\n\r\nPrévoir la taxe pour l'enlèvement des ordures ménagères en plus du loyer de 25 euros/mois.\r\n\r\nVisite virtuelle disponible sur cette annonce ou en copiant ce lien :\r\n\r\n\r\nAppartement avec un Diagnostic de Performance Énergétique classe B : Montant estimé des dépenses annuelles d'énergie pour un usage standard : entre 518 euros et 702 euros par an. Prix moyens des énergies indexés au 01/01/2021 (abonnement compris).\r\n\r\nChauffage individuel électrique.\r\nEau chaude individuelle électrique.\r\n\r\nLes informations sur les risques auxquels ce bien est exposé sont disponibles sur le site Géorisques : \r\n\r\nIMPORTANT : Pour toute demande d'information ou pour déposer votre dossier, merci de nous envoyer un mail depuis l'annonce. Vous recevrez alors un formulaire à remplir. À réception, nous ne manquerons pas de revenir vers vous.\r\n\r\nDisponible dès le 08 Janvier 2026.\r\nLe gestionnaire de cet appartement est Julien.",
      "texts": [
        {
          "text": "SECTEUR - Redon - Agréable appartement Type 2 de 57m² meublé et climatisé avec balcon situé au 1er étage avec ascenseur au 31 rue Nicole Zemmour dans le 9e arrondissement de Marseille. Parking libre dans la résidence fermée et sécurisée. \r\n\r\nCet appartement se compose d'une entrée, d'un grand séjour avec cuisine ouverte entièrement équipée donnant sur une terrasse, une chambre et d'une salle d'eau avec toilettes.\r\n\r\nÀ proximité des arrêts de bus (24/48), du parc de la colline saint Joseph, des commerces et de l'hopital Clairval.\r\n\r\nPrévoir la taxe pour l'enlèvement des ordures ménagères en plus du loyer de 25 euros/mois.\r\n\r\nVisite virtuelle disponible sur cette annonce ou en copiant ce lien :\r\n\r\n\r\nAppartement avec un Diagnostic de Performance Énergétique classe B : Montant estimé des dépenses annuelles d'énergie pour un usage standard : entre 518 euros et 702 euros par an. Prix moyens des énergies indexés au 01/01/2021 (abonnement compris).\r\n\r\nChauffage individuel électrique.\r\nEau chaude individuelle électrique.\r\n\r\nLes informations sur les risques auxquels ce bien est exposé sont disponibles sur le site Géorisques : \r\n\r\nIMPORTANT : Pour toute demande d'information ou pour déposer votre dossier, merci de nous envoyer un mail depuis l'annonce. Vous recevrez alors un formulaire à remplir. À réception, nous ne manquerons pas de revenir vers vous.\r\n\r\nDisponible dès le 08 Janvier 2026.\r\nLe gestionnaire de cet appartement est Julien."
        }
      ],
      "headline": "Meublé"
    },
    "hardFacts": {
      "title": "Appartement à louer",
      "keyfacts": [
        "2 pièces",
        "1 chambre",
        "57 m²",
        "1er étage"
      ],
      "facts": [
        {
          "type": "numberOfRooms",
          "value": "2 pièces",
          "splitValue": "2",
          "label": "pièces"
        },
        {
          "type": "numberOfBedrooms",
          "value": "1 chambre",
          "splitValue": "1",
          "label": "chambre"
        },
        {
          "type": "livingSpace",
          "value": "57 m²",
          "splitValue": "57",
          "label": "m²"
        },
        {
          "type": "numberOfFloors",
          "value": "1er étage",
          "splitValue": "1er",
          "label": "étage"
        }
      ],
      "price": {
        "value": "1 000 €",
        "formatted": "1 000 €/mois",
        "modifiers": "/mois",
        "unitPostfix": {
          "unitTime": "/mois"
        },
        "additionalInformation": "charges comprises",
        "addition": {
          "value": "cc",
          "priceLabelDesc": "charges comprises"
        },
        "financialLink": {
          "href": "https://www.nextories.com/partner/landing/seloger?utm_source=seloger&utm_medium=nativelien-prix-loc-2&utm_campaign=nativelienprix-pagesdetails-seloger-location2",
          "label": "Demander un financement",
          "partnerName": "NEXTORIES_RESERVEZ"
        },
        "ariaLabel": "1000 €",
        "chargesLabel": "cc"
      }
    },
    "energy": {
      "features": [
        {
          "type": "heatingSystem",
          "label": "Type de chauffage",
          "value": "Chauffage individuel"
        },
        {
          "type": "energySource",
          "label": "Sources d'énergie",
          "value": "Gaz"
        }
      ],
      "certificates": [
        {
          "key": "42d3b6e1-ef85-455b-867e-3a51c9ac8758",
          "features": [
            {
              "type": "nameOfCertificate",
              "label": "Diagnostic réalisé",
              "value": "Après le 1er juillet 2021"
            }
          ],
          "scales": [
            {
              "key": "84f43df1-50be-43ea-a7c7-c83b154d71b0",
              "efficiencyClass": {
                "index": 1,
                "rating": "B"
              },
              "values": [
                {
                  "value": "75 kWh/m².an",
                  "label": "Consommation (énergie primaire)"
                },
                {
                  "value": "10 kg CO₂/m².an",
                  "label": "Émissions"
                }
              ],
              "name": "Diagnostic de performance énergétique (DPE)",
              "segments": [
                {
                  "label": "A",
                  "value": ""
                },
                {
                  "label": "B",
                  "value": ""
                },
                {
                  "label": "C",
                  "value": ""
                },
                {
                  "label": "D",
                  "value": ""
                },
                {
                  "label": "E",
                  "value": ""
                },
                {
                  "label": "F",
                  "value": "Passoire énergétique"
                },
                {
                  "label": "G",
                  "value": "Passoire énergétique"
                }
              ],
              "type": "FR_ENERGY_AFTER_2021",
              "ariaLabel": "EfficiencyClass : B avec une plage allant de A à G .La consommation d'énergie est undefined kWhEP/m².an kilowattheures par mètre carré.",
              "displayUnhappyHouseIcon": false
            },
            {
              "key": "0351662f-fdd6-4dd8-8d58-c36403ffcebe",
              "efficiencyClass": {
                "index": 1,
                "rating": "B"
              },
              "values": [
                {
                  "value": "10 kg CO₂/m².an",
                  "label": "Émissions"
                }
              ],
              "name": "Indice d'émission de gaz à effet de serre (GES)",
              "segments": [
                {
                  "label": "A",
                  "value": ""
                },
                {
                  "label": "B",
                  "value": ""
                },
                {
                  "label": "C",
                  "value": ""
                },
                {
                  "label": "D",
                  "value": ""
                },
                {
                  "label": "E",
                  "value": ""
                },
                {
                  "label": "F",
                  "value": ""
                },
                {
                  "label": "G",
                  "value": ""
                }
              ],
              "type": "FR_GHG_AFTER_2021",
              "ariaLabel": "EfficiencyClass : B avec une plage allant de A à G .La consommation d'énergie est undefined kWhEP/m².an kilowattheures par mètre carré.",
              "displayUnhappyHouseIcon": false
            }
          ]
        }
      ],
      "hasScales": true
    },
    "key": {
      "keys": [
        {
          "label": "Identifiant",
          "value": "256170979"
        },
        {
          "label": "Référence annonce",
          "value": "L250662"
        }
      ]
    },
    "price": {
      "base": {
        "main": {
          "label": "Loyer charges comprises",
          "value": "1 000 €/mois Loyer charges comprises",
          "ariaLabel": "1000 €/mois Loyer charges comprises"
        },
        "details": [
          {
            "label": "Coûts supplémentaires",
            "value": "70 €/mois",
            "ariaLabel": "70 €"
          },
          {
            "label": "Prix ​​au m²",
            "value": "17,54 €/mois/m²",
            "ariaLabel": "17,54 euros par mètre carré"
          },
          {
            "label": "Dépôt de garantie",
            "value": "1860"
          }
        ]
      }
    },
    "coOwnership": {
      "items": []
    },
    "features": {
      "preview": [
        {
          "icon": "availability",
          "value": "disponible à partir du 08/01/2026"
        },
        {
          "icon": "floors",
          "value": "1er étage"
        },
        {
          "icon": "kitchen",
          "value": "Cuisine ouverte, Cuisine intégrée"
        },
        {
          "icon": "elevator",
          "value": "Ascenseur"
        },
        {
          "icon": "parking-lots",
          "value": "Parking"
        },
        {
          "icon": "toilet-amenities",
          "value": "1 WC"
        },
        {
          "icon": "balcony",
          "value": "Balcon"
        },
        {
          "icon": "terrace",
          "value": "Terrasse"
        }
      ],
      "details": {
        "categories": [
          {
            "elements": [
              {
                "icon": "availability",
                "value": "disponible à partir du 08/01/2026"
              },
              {
                "value": "12 mois",
                "icon": "rental-time"
              },
              {
                "icon": "furnished",
                "value": "Meublé"
              },
              {
                "icon": "floors",
                "value": "1er étage"
              }
            ],
            "title": "Informations générales"
          },
          {
            "elements": [
              {
                "icon": "elevator",
                "value": "Ascenseur"
              }
            ],
            "title": "Accessibilité"
          },
          {
            "elements": [
              {
                "icon": "kitchen",
                "value": "Cuisine ouverte, Cuisine intégrée"
              },
              {
                "icon": "bathroom-amenities",
                "value": "1 salle de douches"
              },
              {
                "icon": "toilet-amenities",
                "value": "1 WC"
              },
              {
                "icon": "bedroom",
                "value": "1 chambre"
              },
              {
                "icon": "separateEntrance",
                "value": "Entrée séparée"
              }
            ],
            "title": "Intérieur"
          },
          {
            "elements": [
              {
                "icon": "balcony",
                "value": "Balcon"
              },
              {
                "icon": "terrace",
                "value": "Terrasse"
              },
              {
                "icon": "parking-lots",
                "value": "Parking"
              }
            ],
            "title": "Extérieur"
          }
        ]
      }
    },
    "gallery": {
      "images": [
        {
          "key": "d3441f77-f160-495c-85cc-072c4076c9e6",
          "url": "https://mms.seloger.com/d/3/4/4/d3441f77-f160-495c-85cc-072c4076c9e6.jpg?ci_seal=720453d5fe4960f9bf536eae73064226ecba96de",
          "alt": "Appartement à louer 1 000 € 2 pièces 1 chambre 57 m² 1er étage Le Redon Marseille 9ème 13009",
          "classification": {
            "name": "BALCONY",
            "version": "scene-classification-sagemaker-endpoint-live-1-3-10"
          }
        },
        {
          "key": "dd6e1820-dd41-415c-8e00-e322bba730a3",
          "url": "https://mms.seloger.com/d/d/6/e/dd6e1820-dd41-415c-8e00-e322bba730a3.jpg?ci_seal=c95fe3fe46bb8c8ae501c33e0905d2c3bf2b7a41",
          "classification": {
            "name": "LIVING_ROOM",
            "version": "scene-classification-sagemaker-endpoint-live-1-3-10"
          }
        },
        {
          "key": "8365376b-4fdf-4e73-8322-141cf1f0675c",
          "url": "https://mms.seloger.com/8/3/6/5/8365376b-4fdf-4e73-8322-141cf1f0675c.jpg?ci_seal=9e1508e19a4c2ad8bff95d11261249c48f5869f4",
          "classification": {
            "name": "LIVING_ROOM",
            "version": "scene-classification-sagemaker-endpoint-live-1-3-10"
          }
        },
        {
          "key": "c2235810-7000-423c-8c37-3a3bc747d486",
          "url": "https://mms.seloger.com/c/2/2/3/c2235810-7000-423c-8c37-3a3bc747d486.jpg?ci_seal=ef7add158433e3066ae07bc7ae6b7afaa24e71ef",
          "classification": {
            "name": "LIVING_ROOM",
            "version": "scene-classification-sagemaker-endpoint-live-1-3-10"
          }
        },
        {
          "key": "46a52c17-8262-4c70-b864-70e8d5cdb08a",
          "url": "https://mms.seloger.com/4/6/a/5/46a52c17-8262-4c70-b864-70e8d5cdb08a.jpg?ci_seal=a17f6d7b40c26ce270582a426fa77136a82e83e1",
          "classification": {
            "name": "LIVING_ROOM",
            "version": "scene-classification-sagemaker-endpoint-live-1-3-10"
          }
        },
        {
          "key": "8dbf7539-6bfe-48ed-84c7-d8a20af0d65e",
          "url": "https://mms.seloger.com/8/d/b/f/8dbf7539-6bfe-48ed-84c7-d8a20af0d65e.jpg?ci_seal=732596bfc6a2b130b69692daccf61889b6bf20dc",
          "classification": {
            "name": "BEDROOM",
            "version": "scene-classification-sagemaker-endpoint-live-1-3-10"
          }
        },
        {
          "key": "2c1ce04c-8a02-430a-b5ee-8883fe3fc612",
          "url": "https://mms.seloger.com/2/c/1/c/2c1ce04c-8a02-430a-b5ee-8883fe3fc612.jpg?ci_seal=eca45405ae1eb9e25597a59e7466381f0be06838",
          "classification": {
            "name": "KITCHEN",
            "version": "scene-classification-sagemaker-endpoint-live-1-3-10"
          }
        },
        {
          "key": "fbcb61bc-4ae3-4d52-9b7f-60c2f851f9c2",
          "url": "https://mms.seloger.com/f/b/c/b/fbcb61bc-4ae3-4d52-9b7f-60c2f851f9c2.jpg?ci_seal=073ff05495aede131f09279417f9169f019b0fd8",
          "classification": {
            "name": "BATHROOM",
            "version": "scene-classification-sagemaker-endpoint-live-1-3-10"
          }
        }
      ]
    },
    "documents": {
      "display": false,
      "files": []
    },
    "enrichedMedia": {
      "medias": []
    },
    "mortgage": {
      "brand": "seloger",
      "id": "256170979",
      "federalStateGeoId": "AD04FR33",
      "zip": "13009",
      "city": "Marseille 9ème",
      "country": "FRA",
      "region": "Provence-Alpes-Côte d'Azur",
      "showRentLabel": true,
      "showMonthlyRateLabel": false,
      "price": 0,
      "prov": 0,
      "monthlyAmount": 0,
      "formattedMonthlyAmount": "0"
    },
    "partnerAd": {
      "showPartnerAd": false
    },
    "sellerLeadLink": {},
    "priceComparison": {
      "data": {
        "value": 17.77,
        "accuracy": 4,
        "high": "27,92",
        "low": "13,63"
      },
      "markerPosition": 27,
      "hasMainPrice": true,
      "isSale": false,
      "pricePerSqm": "17,54",
      "legalText": "Le prix au m2 est automatiquement calculé par Se Loger en fonction du prix de vente et du nombre de m2 du bien. La comparaison est réalisée à partir des informations relatives au prix du marché sur le même secteur dont dispose Se Loger. Cette information ne préjuge en aucun cas de l'évaluation du bien, qui dépend de son état, ses caractéristiques et de sa localisation."
    },
    "mainDescription": {
      "headline": "Meublé",
      "description": "SECTEUR - Redon - Agréable appartement Type 2 de 57m² meublé et climatisé avec balcon situé au 1er étage avec ascenseur au 31 rue Nicole Zemmour dans le 9e arrondissement de Marseille. Parking libre dans la résidence fermée et sécurisée. \r\n\r\nCet appartement se compose d'une entrée, d'un grand séjour avec cuisine ouverte entièrement équipée donnant sur une terrasse, une chambre et d'une salle d'eau avec toilettes.\r\n\r\nÀ proximité des arrêts de bus (24/48), du parc de la colline saint Joseph, des commerces et de l'hopital Clairval.\r\n\r\nPrévoir la taxe pour l'enlèvement des ordures ménagères en plus du loyer de 25 euros/mois.\r\n\r\nVisite virtuelle disponible sur cette annonce ou en copiant ce lien :\r\n\r\n\r\nAppartement avec un Diagnostic de Performance Énergétique classe B : Montant estimé des dépenses annuelles d'énergie pour un usage standard : entre 518 euros et 702 euros par an. Prix moyens des énergies indexés au 01/01/2021 (abonnement compris).\r\n\r\nChauffage individuel électrique.\r\nEau chaude individuelle électrique.\r\n\r\nLes informations sur les risques auxquels ce bien est exposé sont disponibles sur le site Géorisques : \r\n\r\nIMPORTANT : Pour toute demande d'information ou pour déposer votre dossier, merci de nous envoyer un mail depuis l'annonce. Vous recevrez alors un formulaire à remplir. À réception, nous ne manquerons pas de revenir vers vous.\r\n\r\nDisponible dès le 08 Janvier 2026.\r\nLe gestionnaire de cet appartement est Julien.",
      "metadata": {
        "language": "fr"
      }
    },
    "areaDescription": {
      "headline": "Emplacement"
    },
    "extendedInfoDescription": {
      "headline": "Informations supplémentaires"
    },
    "statistics": {
      "published": "3 heures en ligne",
      "views": "19 vues",
      "saves": "0 favori"
    }
  },
  "contactSections": {
    "id": "25CIEA6XFL6E",
    "legacyId": "256170979",
    "brand": "seloger",
    "agencyId": "RC-026443",
    "static": {
      "phoneNumbers": [
        "06.67.94.37.10"
      ]
    },
    "sticky": {
      "phoneNumbers": [
        "06.67.94.37.10"
      ]
    },
    "contactCard": {
      "title": "IMMOBILIERE PUJOL",
      "subtitle": "Immobiliere Pujol",
      "phoneNumbers": [
        "06.67.94.37.10"
      ],
      "isPrivateOwner": false,
      "agencyLogo": {
        "logoUrl": "https://mms.seloger.com/1/2/7/a/127a2b77-9d00-4613-827d-4dd06b92cc0e.jpg?ci_seal=277b53d8c99f1cc29343330ac17f79a6852358a1",
        "display": true
      },
      "contactLogo": {
        "logoUrl": null,
        "display": false
      },
      "rating": 4.8
    },
    "contactForm": {
      "contactCard": {
        "title": "IMMOBILIERE PUJOL",
        "subtitle": "Immobiliere Pujol",
        "phoneNumbers": [
          "06.67.94.37.10"
        ],
        "isPrivateOwner": false,
        "logoUrl": "https://mms.seloger.com/1/2/7/a/127a2b77-9d00-4613-827d-4dd06b92cc0e.jpg?ci_seal=277b53d8c99f1cc29343330ac17f79a6852358a1"
      },
      "displayOwnerFlag": true,
      "subjectLabel": "Votre message à Immobiliere Pujol",
      "shouldSendLeadValue": true
    },
    "mobilePhones": {
      "title": "IMMOBILIERE PUJOL",
      "subtitle": "IMMOBILIERE PUJOL",
      "phoneNumbers": [
        "06.67.94.37.10"
      ],
      "logoUrl": null,
      "isPrivateOwner": false
    },
    "provider": {
      "intermediaryCard": {
        "title": "IMMOBILIERE PUJOL",
        "subtitle": "Agence professionnelle",
        "display": true,
        "logoUrl": "https://mms.seloger.com/1/2/7/a/127a2b77-9d00-4613-827d-4dd06b92cc0e.jpg?ci_seal=277b53d8c99f1cc29343330ac17f79a6852358a1",
        "logoHref": "https://www.seloger.com/professionnels/agences-immobilieres/marseille-6eme-arrondissement-13006/agence-65904/"
      },
      "contactCard": {
        "title": "Immobiliere Pujol",
        "subtitle": "Votre contact",
        "display": true,
        "logoUrl": null
      },
      "website": "http://www.immobiliere-pujol.fr/",
      "isPrivateOwner": false,
      "profileUrl": "https://www.seloger.com/professionnels/agences-immobilieres/marseille-6eme-arrondissement-13006/agence-65904/",
      "imprintUrl": null,
      "feeUrl": "https://www.immobiliere-pujol.fr/mentions-legales-immobiliere-pujol/",
      "agencyLegalInformations": [
        "SARL IMMOBILIERE PUJOL au capital de 37 000 €",
        "Carte professionnelle A06-758 délivrée par la Préfecture de MARSEILLE",
        "Garantie financière GFC pour un montant de 110 000 €",
        "<b>Siège:</b> 7 rue du Docteur Jean Fiolle, 13006 MARSEILLE",
        "<b>RCS:</b> MARSEILLE 056808868",
        "<b>SIRET:</b> 05680886800048"
      ],
      "publisherType": "AGENCY",
      "rating": {
        "rating": 4.8,
        "reviews": 438,
        "link": "https://www.seloger.com/professionnels/agences-immobilieres/marseille-6eme-arrondissement-13006/agence-65904/#?avisImmo=true"
      },
      "displayLinks": true,
      "address": "7 RUE DU DR FIOLLE, 13006 Marseille 6ème",
      "phoneNumbers": [
        "06.67.94.37.10"
      ]
    },
    "confirmationPage": {
      "isFinanceOfferButtonEnabled": false
    }
  },
  "tracking": {
    "av_category": "classified",
    "av_initiative": "wl_cdp",
    "av_environment": "live",
    "av_estate_type_global": "av_2",
    "av_distribution_type_global": "1",
    "av_client_type": "pro",
    "av_language": "fr",
    "av_zip_code": "13009",
    "av_city": "Marseille 9ème",
    "av_energy_certificate": "B",
    "av_items": [
      {
        "index": 0,
        "name": "classified",
        "list_name": "classified_detail",
        "id": "25CIEA6XFL6E",
        "price": 1000,
        "estate_type": "av_2",
        "distribution_type": "1",
        "country": "France",
        "city": "Marseille 9ème",
        "region": "Provence-Alpes-Côte d'Azur",
        "zip_code": "13009",
        "legacy_id": "256170979",
        "product_type": "standard",
        "client_id": "RC-026443",
        "energy_certificate": "B"
      }
    ]
  },
  "legacyTracking": {
    "site": "SL",
    "pagename": "detail",
    "environment": "prod",
    "language": "fr",
    "temp_variable_1": "WL",
    "products": [
      {
        "client_id": "41952",
        "client_type": "pro",
        "distribution_type": "1",
        "energy_letter": "B",
        "estate_postalcode": "13009",
        "estate_type": 1,
        "id": "256170979",
        "id_duo": 256170979,
        "id_solo": 256170979,
        "list_name": "detail",
        "media": 0,
        "nb_bedrooms": 1,
        "nb_rooms": 2,
        "parent_site": "SL",
        "photos_nb": 8,
        "position": 0,
        "price": 1000,
        "product_geolocation": "localisation_street",
        "product_type": "estate",
        "product_variant": "classified",
        "space": 57
      }
    ]
  },
  "advertising": {
    "slots_config": [
      {
        "id": "div-gam-ad-desktop-top-banner",
        "adUnit": "/199043128/360-seloger/location/general/page-de-detail/leaderboard",
        "size": [
          728,
          90
        ],
        "specificTargeting": {
          "pos": "leaderboard"
        },
        "device": "desktop"
      },
      {
        "id": "ad-medium-rectangle-1",
        "adUnit": "/199043128/360-seloger/location/general/page-de-detail/pave-haut",
        "size": [
          [
            300,
            250
          ],
          "fluid"
        ],
        "specificTargeting": {
          "pos": "pave-haut"
        },
        "device": "desktop"
      },
      {
        "id": "ad-medium-rectangle-2",
        "adUnit": "/199043128/360-seloger/location/general/page-de-detail/pave-bas",
        "size": [
          [
            300,
            250
          ],
          "fluid"
        ],
        "specificTargeting": {
          "pos": "pave-bas"
        },
        "device": "desktop"
      },
      {
        "id": "ad-masonry",
        "adUnit": "/199043128/360-seloger/location/general/page-de-detail/image-galerie",
        "size": [
          [
            624,
            468
          ],
          [
            300,
            250
          ]
        ],
        "specificTargeting": {
          "pos": "image-galerie"
        },
        "device": "desktop"
      },
      {
        "id": "ad-carousel",
        "adUnit": "/199043128/360-seloger/location/general/page-de-detail/pave-carrousel",
        "size": [
          [
            624,
            468
          ],
          [
            300,
            250
          ]
        ],
        "specificTargeting": {
          "pos": "pave-carrousel"
        },
        "device": "desktop"
      },
      {
        "id": "ad-banner-mobile",
        "adUnit": "/199043128/360-seloger/location/general/page-de-detail/banniere-mobile",
        "size": [
          [
            320,
            50
          ],
          [
            320,
            100
          ],
          [
            320,
            150
          ]
        ],
        "specificTargeting": {
          "pos": "banniere-mobile"
        },
        "device": "mobile"
      },
      {
        "id": "ad-masonry",
        "adUnit": "/199043128/360-seloger/location/general/page-de-detail/image-galerie",
        "size": [
          300,
          250
        ],
        "specificTargeting": {
          "pos": "image-galerie"
        },
        "device": "mobile"
      },
      {
        "id": "ad-carousel",
        "adUnit": "/199043128/360-seloger/location/general/page-de-detail/pave-carrousel",
        "size": [
          300,
          250
        ],
        "specificTargeting": {
          "pos": "pave-carrousel"
        },
        "device": "mobile"
      },
      {
        "id": "rental-link",
        "adUnit": "/199043128/360-seloger/location/general/page-de-detail/lien",
        "size": "fluid",
        "specificTargeting": {
          "pos": "Lien"
        },
        "device": "all"
      },
      {
        "id": "partnerbox-1-commercial",
        "adUnit": "/199043128/360-seloger/location/general/page-de-detail/native1",
        "size": "fluid",
        "specificTargeting": {
          "pos": "native1"
        },
        "device": "all"
      },
      {
        "id": "partnerbox-2-commercial",
        "adUnit": "/199043128/360-seloger/location/general/page-de-detail/native2",
        "size": "fluid",
        "specificTargeting": {
          "pos": "native2"
        },
        "device": "all"
      },
      {
        "id": "partnerbox-3-tools-and-service",
        "adUnit": "/199043128/360-seloger/location/general/page-de-detail/native3",
        "size": "fluid",
        "specificTargeting": {
          "pos": "native3"
        },
        "device": "all"
      },
      {
        "id": "partnerbox-4-tools-and-service",
        "adUnit": "/199043128/360-seloger/location/general/page-de-detail/native4",
        "size": "fluid",
        "specificTargeting": {
          "pos": "native4"
        },
        "device": "all"
      },
      {
        "id": "partnerbox-5-tools-and-service",
        "adUnit": "/199043128/360-seloger/location/general/page-de-detail/native5",
        "size": "fluid",
        "specificTargeting": {
          "pos": "native5"
        },
        "device": "all"
      }
    ],
    "tracking_config": {
      "localite": "13055",
      "cp": "13009",
      "geodp": "13",
      "pays": "250",
      "idtt": "1",
      "idtypebien": "1",
      "naturebien": "1",
      "idtiers": "256170979",
      "prix": 1000,
      "nb_pieces": 2,
      "nb_chambres": 1,
      "surface": 57,
      "commodites": [
        "ascenseur",
        "balcon",
        "Chauffage-individuel",
        "Chauffage-gaz",
        "Cuisine-américaine",
        "Cuisine-équipée",
        "parking%20ouvert",
        "SalleDEau-douche",
        "terrasse"
      ],
      "mensualitefinance": 0,
      "si_parking": 1,
      "DPE": "B"
    }
  },
  "seo": {
    "breadcrumb": {
      "type": "cdp-breadcrumb",
      "name": "breadcrumb",
      "title": "cdp-breadcrumb",
      "slug": "cdp-breadcrumb",
      "links": [
        {
          "order": 1,
          "url": "https://www.seloger.com/",
          "label": "Immobilier",
          "hoverLabel": "Immobilier",
          "serpKey": ""
        },
        {
          "order": 2,
          "url": "https://www.seloger.com/immobilier/pays/locations/bien-appartement/france.htm",
          "label": "Appartements à louer France",
          "hoverLabel": "Appartements à louer France",
          "serpKey": ""
        },
        {
          "order": 3,
          "url": "https://www.seloger.com/immobilier/locations/bien-appartement/provence-alpes-cote-d-azur.htm",
          "label": "Appartements à louer Provence-Alpes-Côte d'Azur",
          "hoverLabel": "Appartements à louer Provence-Alpes-Côte d'Azur",
          "serpKey": ""
        },
        {
          "order": 4,
          "url": "https://www.seloger.com/immobilier/locations/13/bien-appartement/",
          "label": "Appartements à louer Bouches-du-Rhône 13",
          "hoverLabel": "Appartements à louer Bouches-du-Rhône 13",
          "serpKey": ""
        },
        {
          "order": 5,
          "url": "https://www.seloger.com/immobilier/locations/immo-marseille-9eme-13/bien-appartement/",
          "label": "Appartements à louer Marseille 9ème arrondissement 13009",
          "hoverLabel": "Appartements à louer Marseille 9ème arrondissement 13009",
          "serpKey": ""
        },
        {
          "order": 100,
          "url": "",
          "label": "Annonce",
          "hoverLabel": "Annonce",
          "serpKey": ""
        }
      ]
    },
    "headInfo": {
      "title": "Appartement à louer T2/F2 57 m² 1000 € Le Redon Marseille (13009)",
      "titleWithCount": "",
      "description": "Appartement à louer T2/F2 57 m² 1000 € Le Redon Marseille (13009)",
      "canonical": "https://www.seloger.com/annonces/locations/appartement/marseille-9eme-13/le-redon/256170979.htm",
      "robots": "index, follow, max-snippet:-1",
      "icons": [
        {
          "relation": "shortcut icon",
          "link": "https://www.seloger.com/favicon.ico",
          "type": "image/ico"
        }
      ],
      "openGraphs": [
        {
          "property": "locale",
          "content": "fr_FR"
        },
        {
          "property": "url",
          "content": "https://www.seloger.com/annonces/locations/appartement/marseille-9eme-13/le-redon/256170979.htm"
        },
        {
          "property": "type",
          "content": "website"
        },
        {
          "property": "site_name",
          "content": "SeLoger"
        },
        {
          "property": "title",
          "content": "Appartement à louer T2/F2 57 m² 1000 € Le Redon Marseille (13009)"
        },
        {
          "property": "description",
          "content": "Appartement à louer T2/F2 57 m² 1000 € Le Redon Marseille (13009)"
        },
        {
          "property": "image",
          "content": "https://mms.seloger.com/d/3/4/4/d3441f77-f160-495c-85cc-072c4076c9e6.jpg?ci_seal=720453d5fe4960f9bf536eae73064226ecba96de"
        }
      ],
      "socials": [
        {
          "name": "twitter:card",
          "content": "Appartement à louer T2/F2 57 m² 1000 € Le Redon Marseille (13009)"
        },
        {
          "name": "twitter:url",
          "content": "https://www.seloger.com/annonces/locations/appartement/marseille-9eme-13/le-redon/256170979.htm"
        },
        {
          "name": "twitter:site",
          "content": "@seloger"
        },
        {
          "name": "twitter:title",
          "content": "Appartement à louer T2/F2 57 m² 1000 € Le Redon Marseille (13009)"
        },
        {
          "name": "twitter:description",
          "content": "Appartement à louer T2/F2 57 m² 1000 € Le Redon Marseille (13009)"
        },
        {
          "name": "twitter:image",
          "content": "https://mms.seloger.com/d/3/4/4/d3441f77-f160-495c-85cc-072c4076c9e6.jpg?ci_seal=720453d5fe4960f9bf536eae73064226ecba96de"
        }
      ],
      "structuredData": [
        [
          {
            "type": "@context",
            "content": "https://schema.org"
          },
          {
            "type": "@type",
            "content": "Organization"
          },
          {
            "type": "name",
            "content": "SeLoger"
          },
          {
            "type": "address",
            "content": "2 Rue des Italiens, 75009 Paris"
          },
          {
            "type": "telephone",
            "content": "01 53 38 28 00"
          },
          {
            "type": "url",
            "content": "https://www.seloger.com/"
          },
          {
            "type": "logo",
            "content": "https://static-seloger.com/commons/header/logo_header.svg"
          }
        ],
        [
          {
            "type": "@context",
            "content": "https://schema.org"
          },
          {
            "type": "@type",
            "content": "RealEstateListing"
          },
          {
            "type": "datePosted",
            "content": ""
          },
          {
            "type": "description",
            "content": "Appartement à louer T2/F2 57 m² 1000 € Le Redon Marseille (13009)"
          },
          {
            "type": "name",
            "content": "Appartement à louer T2/F2 57 m² 1000 € Le Redon Marseille (13009)"
          }
        ]
      ],
      "breadcrumb": [
        {
          "order": 1,
          "url": "https://www.seloger.com/",
          "label": "Immobilier",
          "hoverLabel": "Immobilier",
          "serpKey": ""
        },
        {
          "order": 2,
          "url": "https://www.seloger.com/immobilier/pays/locations/bien-appartement/france.htm",
          "label": "Appartements à louer France",
          "hoverLabel": "Appartements à louer France",
          "serpKey": ""
        },
        {
          "order": 3,
          "url": "https://www.seloger.com/immobilier/locations/bien-appartement/provence-alpes-cote-d-azur.htm",
          "label": "Appartements à louer Provence-Alpes-Côte d'Azur",
          "hoverLabel": "Appartements à louer Provence-Alpes-Côte d'Azur",
          "serpKey": ""
        },
        {
          "order": 4,
          "url": "https://www.seloger.com/immobilier/locations/13/bien-appartement/",
          "label": "Appartements à louer Bouches-du-Rhône 13",
          "hoverLabel": "Appartements à louer Bouches-du-Rhône 13",
          "serpKey": ""
        },
        {
          "order": 5,
          "url": "https://www.seloger.com/immobilier/locations/immo-marseille-9eme-13/bien-appartement/",
          "label": "Appartements à louer Marseille 9ème arrondissement 13009",
          "hoverLabel": "Appartements à louer Marseille 9ème arrondissement 13009",
          "serpKey": ""
        }
      ],
      "redirectUrl": "https://www.seloger.com/annonces/locations/appartement/marseille-9eme-13/le-redon/256170979.htm"
    }
  },
  "farbwelt": {
    "color": "#b0d050",
    "textColor": "dark",
    "providerName": "IMMOBILIERE PUJOL",
    "logo": {
      "src": "https://mms.seloger.com/1/2/7/a/127a2b77-9d00-4613-827d-4dd06b92cc0e.jpg?ci_seal=277b53d8c99f1cc29343330ac17f79a6852358a1",
      "alt": "logo-RC-026443",
      "extension": ""
    },
    "teasers": [
      {
        "type": "MediumRectangleTop",
        "image": {
          "src": "https://cdnihddipa.cloudimg.io/2/c/f/8/2cf88a51-024d-4568-8256-46f77f947d41.png?ci_eqs=&ci_seal=947e1481b4e9770d21e7db04b7c2de929997e986",
          "alt": "MediumRectangleTop"
        },
        "linkTarget": {
          "href": "https://www.seloger.com/professionnels/agences-immobilieres/marseille-6eme-arrondissement-13006/agence-65904/",
          "isExternal": false
        }
      },
      {
        "type": "MediumRectangleBottom",
        "image": {
          "src": "https://cdnihddipa.cloudimg.io/2/c/f/8/2cf88a51-024d-4568-8256-46f77f947d41.png?ci_eqs=&ci_seal=947e1481b4e9770d21e7db04b7c2de929997e986",
          "alt": "MediumRectangleBottom"
        },
        "linkTarget": {
          "href": "https://www.seloger.com/professionnels/agences-immobilieres/marseille-6eme-arrondissement-13006/agence-65904/",
          "isExternal": false
        }
      },
      {
        "type": "MobileBanner",
        "image": {
          "src": "https://cdnihddipa.cloudimg.io/9/d/6/f/9d6fd530-c3ba-4539-928a-91e2421e13f2.png?ci_eqs=&ci_seal=e767f2f96dd16cee179ba485c8515dae191a7e7f",
          "alt": "MediumRectangleTop"
        },
        "linkTarget": {
          "href": "https://www.seloger.com/professionnels/agences-immobilieres/marseille-6eme-arrondissement-13006/agence-65904/",
          "isExternal": false
        }
      }
    ]
  },
  "defaultBackToSearch": "distributionTypes=Rent&estateTypes=Apartment&locations=NBH2FR1089&priceMax=1200&priceMin=800",
  "tags": {
    "isExclusive": false,
    "has3DVisit": false,
    "hasBrokerageFee": false,
    "isNew": true,
    "isHdExclusive": false
  },
  "rawData": {
    "distributionType": "RENT",
    "propertyType": "APARTMENT",
    "geoIdHierarchy": [
      {
        "id": "NBH2FR1089",
        "typeKey": "NBH2"
      },
      {
        "id": "AD09FR9",
        "typeKey": "AD09"
      },
      {
        "id": "AD08FR4491",
        "typeKey": "AD08"
      },
      {
        "id": "AD06FR13",
        "typeKey": "AD06"
      },
      {
        "id": "AD04FR33",
        "typeKey": "AD04"
      },
      {
        "id": "AD03FR2",
        "typeKey": "AD03"
      },
      {
        "id": "AD02FR1",
        "typeKey": "AD02"
      }
    ],
    "distributionSubType": {
      "rent": "CLASSIC"
    }
  },
  "cps": "25CIEA6XFL6E"
}